{
    "1": {
        "id": "1",
        "name": "Qlipoth",
        "type": "A Preservação",
        "image": "image/simulated_event/HoshinoKami_001.png"
    },
    "2": {
        "id": "2",
        "name": "Fuli",
        "type": "A Recordação",
        "image": "image/simulated_event/HoshinoKami_006.png"
    },
    "3": {
        "id": "3",
        "name": "IX",
        "type": "A Inexistência",
        "image": "image/simulated_event/HoshinoKami_004.png"
    },
    "4": {
        "id": "4",
        "name": "Yaoshi",
        "type": "A Abundância",
        "image": "image/simulated_event/HoshinoKami_003.png"
    },
    "5": {
        "id": "5",
        "name": "Lan",
        "type": "A Caça",
        "image": "image/simulated_event/HoshinoKami_005.png"
    },
    "6": {
        "id": "6",
        "name": "Nanook",
        "type": "A Destruição",
        "image": "image/simulated_event/HoshinoKami_002.png"
    },
    "7": {
        "id": "7",
        "name": "Aha",
        "type": "A Euforia",
        "image": "image/simulated_event/HoshinoKami_007.png"
    },
    "8": {
        "id": "8",
        "name": "Herta",
        "type": "Sociedade de Gênios #83",
        "image": "image/simulated_event/HoshinoKami_Herta.png"
    },
    "9": {
        "id": "9",
        "name": "Ruan Mei",
        "type": "Sociedade de Gênios #81",
        "image": "image/simulated_event/HoshinoKami_Herta2.png"
    },
    "10": {
        "id": "10",
        "name": "Ena",
        "type": "Ordem",
        "image": "image/simulated_event/HoshinoKami_011.png"
    },
    "11": {
        "id": "11",
        "name": "Xipe",
        "type": "Harmonia",
        "image": "image/simulated_event/HoshinoKami_008.png"
    },
    "12": {
        "id": "12",
        "name": "Oroboros",
        "type": "Voracidade",
        "image": "image/simulated_event/HoshinoKami_010.png"
    },
    "13": {
        "id": "13",
        "name": "Screwllum",
        "type": "Sociedade de Gênios #76",
        "image": "image/simulated_event/HoshinoKami_Herta3.png"
    },
    "14": {
        "id": "14",
        "name": "Tayzzyronth",
        "type": "A Propagação",
        "image": "image/simulated_event/HoshinoKami_009.png"
    },
    "15": {
        "id": "15",
        "name": "Stephen Lloyd",
        "type": "Sociedade de Gênios #84",
        "image": "image/simulated_event/HoshinoKami_Herta4.png"
    },
    "16": {
        "id": "16",
        "name": "Stephen Lloyd",
        "type": "Sociedade de Gênios #84",
        "image": "image/simulated_event/HoshinoKami_Herta5.png"
    },
    "17": {
        "id": "17",
        "name": "Nous",
        "type": "A Erudição",
        "image": "image/simulated_event/HoshinoKami_012.png"
    },
    "18": {
        "id": "18",
        "name": "HooH",
        "type": "O Equilíbrio",
        "image": "image/simulated_event/HoshinoKami_014.png"
    },
    "19": {
        "id": "19",
        "name": "Mythus",
        "type": "O Enigmata",
        "image": "image/simulated_event/HoshinoKami_013.png"
    },
    "20": {
        "id": "20",
        "name": "Polka Kakamond",
        "type": "Sociedade de Gênios #4",
        "image": "image/simulated_event/HoshinoKami_Herta6.png"
    },
    "139": {
        "id": "139",
        "name": "Início: Corporação da Paz Interastral",
        "type": "Segredos",
        "image": "image/simulated_event/RoguePicEventDLC_08.png"
    },
    "140": {
        "id": "140",
        "name": "Julgado como Orgânico: Sócios (I)",
        "type": "Segredos",
        "image": "image/simulated_event/RoguePicEventDLC_09.png"
    },
    "141": {
        "id": "141",
        "name": "Expansão Cognitiva: Sócios (II)",
        "type": "Segredos",
        "image": "image/simulated_event/RoguePicEventDLC_09.png"
    },
    "142": {
        "id": "142",
        "name": "Orgânico Supremo: Condolências Sanguíneas (I)",
        "type": "Segredos",
        "image": "image/simulated_event/RoguePicEventDLC_12.png"
    },
    "143": {
        "id": "143",
        "name": "Orgânico Supremo: Condolências Sanguíneas (II)",
        "type": "Segredos",
        "image": "image/simulated_event/RoguePicEventDLC_12.png"
    },
    "144": {
        "id": "144",
        "name": "Julgado como Inorgânico: Ouro Líquido (I)",
        "type": "Segredos",
        "image": "image/simulated_event/RoguePicEventDLC_10.png"
    },
    "145": {
        "id": "145",
        "name": "Expansão Cognitiva: Ouro Líquido (II)",
        "type": "Segredos",
        "image": "image/simulated_event/RoguePicEventDLC_10.png"
    },
    "146": {
        "id": "146",
        "name": "Inorgânico Supremo: Trono do Universo (I)",
        "type": "Segredos",
        "image": "image/simulated_event/RoguePicEventDLC_10.png"
    },
    "147": {
        "id": "147",
        "name": "Expansão Cognitiva: Trono do Universo (II)",
        "type": "Segredos",
        "image": "image/simulated_event/RoguePicEventDLC_09.png"
    },
    "148": {
        "id": "148",
        "name": "Inorgânico Supremo: Condolências Sanguíneas (III)",
        "type": "Segredos",
        "image": "image/simulated_event/RoguePicEventDLC_12.png"
    },
    "149": {
        "id": "149",
        "name": "Início: O Império Maquinário",
        "type": "Segredos",
        "image": "image/simulated_event/RoguePicEventDLC_07.png"
    },
    "150": {
        "id": "150",
        "name": "Orgânico Supremo: Temperos Metálicos (I)",
        "type": "Segredos",
        "image": "image/simulated_event/RoguePicEventDLC_08.png"
    },
    "151": {
        "id": "151",
        "name": "Expansão Cognitiva: Temperos Metálicos (II)",
        "type": "Segredos",
        "image": "image/simulated_event/RoguePicEventDLC_08.png"
    },
    "152": {
        "id": "152",
        "name": "Julgado como Orgânico: Pensamentos Negativos (I)",
        "type": "Segredos",
        "image": "image/simulated_event/RoguePicEventDLC_07.png"
    },
    "153": {
        "id": "153",
        "name": "Expansão Cognitiva: Pensamentos Negativos (II)",
        "type": "Segredos",
        "image": "image/simulated_event/RoguePicEventDLC_07.png"
    },
    "154": {
        "id": "154",
        "name": "Julgado como Inorgânico: O *Pai* Sofredor (I)",
        "type": "Segredos",
        "image": "image/simulated_event/RoguePicEventDLC_11.png"
    },
    "155": {
        "id": "155",
        "name": "Expansão Cognitiva: O *Pai* Sofredor (II)",
        "type": "Segredos",
        "image": "image/simulated_event/RoguePicEventDLC_11.png"
    },
    "156": {
        "id": "156",
        "name": "Inorgânico Supremo: As Três Revelações de Deus (I)",
        "type": "Segredos",
        "image": "image/simulated_event/RoguePicEventDLC_08.png"
    },
    "157": {
        "id": "157",
        "name": "Orgânico Supremo: As Três Revelações de Deus (II)",
        "type": "Segredos",
        "image": "image/simulated_event/RoguePicEventDLC_11.png"
    },
    "158": {
        "id": "158",
        "name": "Inorgânico Supremo: As Três Revelações de Deus (III)",
        "type": "Segredos",
        "image": "image/simulated_event/RoguePicEventDLC_07.png"
    },
    "159": {
        "id": "159",
        "name": "Os Arquitetos",
        "type": "Equação",
        "image": "image/simulated_event/RoguePicEventTourn_01.png"
    },
    "160": {
        "id": "160",
        "name": "Jardim da Recordação",
        "type": "Equação",
        "image": "image/simulated_event/RoguePicEventTourn_01.png"
    },
    "161": {
        "id": "161",
        "name": "Autoaniquilador",
        "type": "Equação",
        "image": "image/simulated_event/RoguePicEventTourn_01.png"
    },
    "162": {
        "id": "162",
        "name": "Buscadores de Elixir",
        "type": "Equação",
        "image": "image/simulated_event/RoguePicEventTourn_01.png"
    },
    "163": {
        "id": "163",
        "name": "Vigia da Galáxia",
        "type": "Equação",
        "image": "image/simulated_event/RoguePicEventTourn_01.png"
    },
    "164": {
        "id": "164",
        "name": "Legião Antimatéria",
        "type": "Equação",
        "image": "image/simulated_event/RoguePicEventTourn_01.png"
    },
    "165": {
        "id": "165",
        "name": "Tolos Mascarados",
        "type": "Equação",
        "image": "image/simulated_event/RoguePicEventTourn_01.png"
    },
    "166": {
        "id": "166",
        "name": "Progênie da Majestade do Enxame",
        "type": "Equação",
        "image": "image/simulated_event/RoguePicEventTourn_01.png"
    },
    "167": {
        "id": "167",
        "name": "Escola de Ecologia Astral",
        "type": "Equação",
        "image": "image/simulated_event/RoguePicEventTourn_01.png"
    },
    "168": {
        "id": "168",
        "name": "Revitalizador da Cidade",
        "type": "Equação",
        "image": "image/simulated_event/RoguePicEventTourn_01.png"
    },
    "169": {
        "id": "169",
        "name": "Caçador Silencioso",
        "type": "Equação",
        "image": "image/simulated_event/RoguePicEventTourn_01.png"
    },
    "170": {
        "id": "170",
        "name": "Instituto de Auto-Provas",
        "type": "Equação",
        "image": "image/simulated_event/RoguePicEventTourn_01.png"
    },
    "171": {
        "id": "171",
        "name": "Borisin",
        "type": "Equação",
        "image": "image/simulated_event/RoguePicEventTourn_01.png"
    },
    "172": {
        "id": "172",
        "name": "Cavaleiro Derretido",
        "type": "Equação",
        "image": "image/simulated_event/RoguePicEventTourn_01.png"
    },
    "173": {
        "id": "173",
        "name": "Velejador Guardião",
        "type": "Equação",
        "image": "image/simulated_event/RoguePicEventTourn_01.png"
    },
    "174": {
        "id": "174",
        "name": "Médico Conselheiro",
        "type": "Equação",
        "image": "image/simulated_event/RoguePicEventTourn_01.png"
    },
    "175": {
        "id": "175",
        "name": "Herdeiros da Calamidade",
        "type": "Equação",
        "image": "image/simulated_event/RoguePicEventTourn_01.png"
    },
    "176": {
        "id": "176",
        "name": "Erudito Inútil",
        "type": "Equação",
        "image": "image/simulated_event/RoguePicEventTourn_01.png"
    },
    "177": {
        "id": "177",
        "name": "Ladrão Fantasma",
        "type": "Equação",
        "image": "image/simulated_event/RoguePicEventTourn_01.png"
    },
    "178": {
        "id": "178",
        "name": "Mausoléu das Feridas",
        "type": "Equação",
        "image": "image/simulated_event/RoguePicEventTourn_01.png"
    },
    "179": {
        "id": "179",
        "name": "Agregador",
        "type": "Equação",
        "image": "image/simulated_event/RoguePicEventTourn_01.png"
    },
    "180": {
        "id": "180",
        "name": "Salvador Biônico",
        "type": "Equação",
        "image": "image/simulated_event/RoguePicEventTourn_01.png"
    },
    "181": {
        "id": "181",
        "name": "Erudito da Aniquilação",
        "type": "Equação",
        "image": "image/simulated_event/RoguePicEventTourn_01.png"
    },
    "182": {
        "id": "182",
        "name": "Nova Capa (I)",
        "type": "Segredo",
        "image": "image/simulated_event/RoguePicEventDLC_10.png"
    },
    "183": {
        "id": "183",
        "name": "Nova Capa (II)",
        "type": "Segredo",
        "image": "image/simulated_event/RoguePicEventDLC_10.png"
    },
    "184": {
        "id": "184",
        "name": "Nova Capa (III)",
        "type": "Segredo",
        "image": "image/simulated_event/RoguePicEventDLC_10.png"
    },
    "185": {
        "id": "185",
        "name": "Nunca Esquecidos (I)",
        "type": "Segredo",
        "image": "image/simulated_event/RoguePicEventDLC_10.png"
    },
    "186": {
        "id": "186",
        "name": "Nunca Esquecidos (II)",
        "type": "Segredo",
        "image": "image/simulated_event/RoguePicEventDLC_10.png"
    },
    "187": {
        "id": "187",
        "name": "Nunca Esquecidos (III)",
        "type": "Segredo",
        "image": "image/simulated_event/RoguePicEventDLC_10.png"
    },
    "188": {
        "id": "188",
        "name": "Mundo de Dar Corda (I)",
        "type": "Segredo",
        "image": "image/simulated_event/RoguePicEventDLC_10.png"
    },
    "189": {
        "id": "189",
        "name": "Mundo de Dar Corda (II)",
        "type": "Segredo",
        "image": "image/simulated_event/RoguePicEventDLC_10.png"
    },
    "190": {
        "id": "190",
        "name": "Mundo de Dar Corda (III)",
        "type": "Segredo",
        "image": "image/simulated_event/RoguePicEventDLC_10.png"
    },
    "191": {
        "id": "191",
        "name": "Verdades Impressas (I)",
        "type": "Segredo",
        "image": "image/simulated_event/RoguePicEventDLC_10.png"
    },
    "192": {
        "id": "192",
        "name": "Verdades Impressas (II)",
        "type": "Segredo",
        "image": "image/simulated_event/RoguePicEventDLC_10.png"
    },
    "193": {
        "id": "193",
        "name": "Verdades Impressas (III)",
        "type": "Segredo",
        "image": "image/simulated_event/RoguePicEventDLC_10.png"
    },
    "194": {
        "id": "194",
        "name": "A Grande Mentira (I)",
        "type": "Segredo",
        "image": "image/simulated_event/RoguePicEventDLC_10.png"
    },
    "195": {
        "id": "195",
        "name": "A Grande Mentira (II)",
        "type": "Segredo",
        "image": "image/simulated_event/RoguePicEventDLC_10.png"
    },
    "196": {
        "id": "196",
        "name": "A Grande Mentira (III)",
        "type": "Segredo",
        "image": "image/simulated_event/RoguePicEventDLC_10.png"
    },
    "197": {
        "id": "197",
        "name": "Extinção das Chamas (I)",
        "type": "Segredo",
        "image": "image/simulated_event/RoguePicEventDLC_10.png"
    },
    "198": {
        "id": "198",
        "name": "Extinção das Chamas (II)",
        "type": "Segredo",
        "image": "image/simulated_event/RoguePicEventDLC_10.png"
    },
    "199": {
        "id": "199",
        "name": "Extinção das Chamas (III)",
        "type": "Segredo",
        "image": "image/simulated_event/RoguePicEventDLC_10.png"
    },
    "200": {
        "id": "200",
        "name": "Gênio e Profecia (I)",
        "type": "Segredo",
        "image": "image/simulated_event/RoguePicEventDLC_13.png"
    },
    "201": {
        "id": "201",
        "name": "Gênio e Profecia (II)",
        "type": "Segredo",
        "image": "image/simulated_event/RoguePicEventDLC_13.png"
    },
    "202": {
        "id": "202",
        "name": "Congresso Futurológico (I)",
        "type": "Segredo",
        "image": "image/simulated_event/RoguePicEventDLC_13.png"
    },
    "203": {
        "id": "203",
        "name": "Congresso Futurológico (II)",
        "type": "Segredo",
        "image": "image/simulated_event/RoguePicEventDLC_13.png"
    },
    "204": {
        "id": "204",
        "name": "Congresso Futurológico (III)",
        "type": "Segredo",
        "image": "image/simulated_event/RoguePicEventDLC_13.png"
    },
    "205": {
        "id": "205",
        "name": "Falência Onipotente (I)",
        "type": "Segredo",
        "image": "image/simulated_event/RoguePicEventDLC_13.png"
    },
    "206": {
        "id": "206",
        "name": "Falência Onipotente (II)",
        "type": "Segredo",
        "image": "image/simulated_event/RoguePicEventDLC_13.png"
    },
    "207": {
        "id": "207",
        "name": "Falência Onipotente (III)",
        "type": "Segredo",
        "image": "image/simulated_event/RoguePicEventDLC_13.png"
    },
    "208": {
        "id": "208",
        "name": "Vírus Antiorgânico (I)",
        "type": "Segredo",
        "image": "image/simulated_event/RoguePicEventDLC_13.png"
    },
    "209": {
        "id": "209",
        "name": "Vírus Antiorgânico (II)",
        "type": "Segredo",
        "image": "image/simulated_event/RoguePicEventDLC_13.png"
    },
    "210": {
        "id": "210",
        "name": "Vírus Antiorgânico (III)",
        "type": "Segredo",
        "image": "image/simulated_event/RoguePicEventDLC_13.png"
    },
    "211": {
        "id": "211",
        "name": "Protesto de Izmael (I)",
        "type": "Segredo",
        "image": "image/simulated_event/RoguePicEventDLC_13.png"
    },
    "212": {
        "id": "212",
        "name": "Protesto de Izmael (II)",
        "type": "Segredo",
        "image": "image/simulated_event/RoguePicEventDLC_13.png"
    },
    "213": {
        "id": "213",
        "name": "Protesto de Izmael (III)",
        "type": "Segredo",
        "image": "image/simulated_event/RoguePicEventDLC_13.png"
    },
    "214": {
        "id": "214",
        "name": "Cognição Desmoronada (I)",
        "type": "Segredo",
        "image": "image/simulated_event/RoguePicEventDLC_13.png"
    },
    "215": {
        "id": "215",
        "name": "Cognição Desmoronada (II)",
        "type": "Segredo",
        "image": "image/simulated_event/RoguePicEventDLC_13.png"
    },
    "216": {
        "id": "216",
        "name": "Cognição Desmoronada (III)",
        "type": "Segredo",
        "image": "image/simulated_event/RoguePicEventDLC_13.png"
    },
    "217": {
        "id": "217",
        "name": "Espiando o Paraíso (I)",
        "type": "Segredo",
        "image": "image/simulated_event/RoguePicEventDLC_13.png"
    },
    "218": {
        "id": "218",
        "name": "Espiando o Paraíso (II)",
        "type": "Segredo",
        "image": "image/simulated_event/RoguePicEventDLC_13.png"
    },
    "219": {
        "id": "219",
        "name": "Espiando o Paraíso (III)",
        "type": "Segredo",
        "image": "image/simulated_event/RoguePicEventDLC_13.png"
    },
    "220": {
        "id": "220",
        "name": "Expectativa de Aeons",
        "type": "Segredo",
        "image": "image/simulated_event/RoguePicEventDLC_13.png"
    },
    "221": {
        "id": "221",
        "name": "Domínio Incógnito (I)",
        "type": "Segredo",
        "image": "image/simulated_event/RoguePicEventDLC_13.png"
    },
    "222": {
        "id": "222",
        "name": "Domínio Incógnito (II)",
        "type": "Segredo",
        "image": "image/simulated_event/RoguePicEventDLC_13.png"
    },
    "223": {
        "id": "223",
        "name": "Traçador Relativo",
        "type": "Equação",
        "image": "image/simulated_event/RoguePicEventTourn_01.png"
    },
    "224": {
        "id": "224",
        "name": "Verme Distorcestrelas",
        "type": "Equação",
        "image": "image/simulated_event/RoguePicEventTourn_01.png"
    },
    "225": {
        "id": "225",
        "name": "Gigante Sem Coração",
        "type": "Equação",
        "image": "image/simulated_event/RoguePicEventTourn_01.png"
    },
    "226": {
        "id": "226",
        "name": "Catador de Ervas",
        "type": "Equação",
        "image": "image/simulated_event/RoguePicEventTourn_01.png"
    },
    "227": {
        "id": "227",
        "name": "Borboleta Em Um Galho",
        "type": "Segredo",
        "image": "image/simulated_event/RoguePicEventTourn_02.png"
    },
    "228": {
        "id": "228",
        "name": "A Borboleta Voa Pela Janela",
        "type": "Segredo",
        "image": "image/simulated_event/RoguePicEventTourn_02.png"
    },
    "229": {
        "id": "229",
        "name": "Borboleta Parte Em Silêncio",
        "type": "Segredo",
        "image": "image/simulated_event/RoguePicEventTourn_02.png"
    },
    "230": {
        "id": "230",
        "name": "Quando O Fruto Do Destino Caiu",
        "type": "Segredo",
        "image": "image/simulated_event/RoguePicEventTourn_02.png"
    },
    "231": {
        "id": "231",
        "name": "Quando Os Passos Do Destino Cessaram",
        "type": "Segredo",
        "image": "image/simulated_event/RoguePicEventTourn_02.png"
    },
    "232": {
        "id": "232",
        "name": "Quando O Destino Revelou O Caminho",
        "type": "Segredo",
        "image": "image/simulated_event/RoguePicEventTourn_02.png"
    },
    "233": {
        "id": "233",
        "name": "Carnaval do Céu e Terra",
        "type": "Segredo",
        "image": "image/simulated_event/RoguePicEventTourn_02.png"
    },
    "234": {
        "id": "234",
        "name": "Canção da Chuva e da Neve",
        "type": "Segredo",
        "image": "image/simulated_event/RoguePicEventTourn_02.png"
    },
    "235": {
        "id": "235",
        "name": "Valsa do Vento e das Marés",
        "type": "Segredo",
        "image": "image/simulated_event/RoguePicEventTourn_02.png"
    },
    "236": {
        "id": "236",
        "name": "A Divindade Que Enganou As Divindades",
        "type": "Segredo",
        "image": "image/simulated_event/RoguePicEventTourn_02.png"
    },
    "237": {
        "id": "237",
        "name": "A Divindade que Provocava Mortais",
        "type": "Segredo",
        "image": "image/simulated_event/RoguePicEventTourn_02.png"
    },
    "238": {
        "id": "238",
        "name": "A Divindade da Desordem e do Caos",
        "type": "Segredo",
        "image": "image/simulated_event/RoguePicEventTourn_02.png"
    },
    "239": {
        "id": "239",
        "name": "A Guerra que Nunca Cessou",
        "type": "Segredo",
        "image": "image/simulated_event/RoguePicEventTourn_02.png"
    },
    "240": {
        "id": "240",
        "name": "Guerra Que Continua",
        "type": "Segredo",
        "image": "image/simulated_event/RoguePicEventTourn_02.png"
    },
    "241": {
        "id": "241",
        "name": "A Guerra que Perdeu Sua Glória",
        "type": "Segredo",
        "image": "image/simulated_event/RoguePicEventTourn_02.png"
    },
    "242": {
        "id": "242",
        "name": "Canção de Ninar para Crianças",
        "type": "Segredo",
        "image": "image/simulated_event/RoguePicEventTourn_02.png"
    },
    "243": {
        "id": "243",
        "name": "Canção de Ninar para Alertar o Mundo",
        "type": "Segredo",
        "image": "image/simulated_event/RoguePicEventTourn_02.png"
    },
    "244": {
        "id": "244",
        "name": "Canção de Ninar Para Voltar Ao Lar",
        "type": "Segredo",
        "image": "image/simulated_event/RoguePicEventTourn_02.png"
    },
    "398": {
        "id": "398",
        "name": "Ideia de Stephen Lloyd",
        "type": "Ocorrência",
        "image": "image/simulated_event/PicRogueEvent_Normal.png"
    },
    "10000": {
        "id": "10000",
        "name": "Área de Descanso",
        "type": "Trégua",
        "image": "image/simulated_event/HoshinoKami_Herta.png"
    },
    "10001": {
        "id": "10001",
        "name": "Área de Descanso",
        "type": "Trégua",
        "image": "image/simulated_event/HoshinoKami_Herta.png"
    },
    "10002": {
        "id": "10002",
        "name": "Área de Descanso",
        "type": "Trégua",
        "image": "image/simulated_event/HoshinoKami_Herta.png"
    },
    "10101": {
        "id": "10101",
        "name": "Mineradores Nômades",
        "type": "Ocorrência",
        "image": "image/simulated_event/PicRogueEvent_Normal.png"
    },
    "10201": {
        "id": "10201",
        "name": "Ficciologistas da História",
        "type": "Ocorrência",
        "image": "image/simulated_event/PicRogueEvent_Historian.png"
    },
    "10202": {
        "id": "10202",
        "name": "Ficciologistas da História",
        "type": "Ocorrência",
        "image": "image/simulated_event/PicRogueEvent_Historian.png"
    },
    "10301": {
        "id": "10301",
        "name": "Jim Hulk e Jim Hall",
        "type": "Ocorrência",
        "image": "image/simulated_event/PicRogueEvent_Normal.png"
    },
    "10401": {
        "id": "10401",
        "name": "Canal de Compras",
        "type": "Ocorrência",
        "image": "image/simulated_event/PicRogueEvent_Normal.png"
    },
    "10501": {
        "id": "10501",
        "name": "Os Cremadores",
        "type": "Ocorrência",
        "image": "image/simulated_event/PicRogueEvent_Normal.png"
    },
    "10601": {
        "id": "10601",
        "name": "Artes Interativas",
        "type": "Ocorrência",
        "image": "image/simulated_event/PicRogueEvent_Normal.png"
    },
    "10701": {
        "id": "10701",
        "name": "Mundo Pixelado",
        "type": "Ocorrência",
        "image": "image/simulated_event/PicRogueEvent_Pixel.png"
    },
    "10801": {
        "id": "10801",
        "name": "Pelúcia de Aha",
        "type": "Ocorrência",
        "image": "image/simulated_event/PicRogueEvent_Toy.png"
    },
    "10901": {
        "id": "10901",
        "name": "Dispensador de Promissórias",
        "type": "Ocorrência",
        "image": "image/simulated_event/PicRogueEvent_Bond.png"
    },
    "10902": {
        "id": "10902",
        "name": "Dispensador de Promissórias",
        "type": "Ocorrência",
        "image": "image/simulated_event/PicRogueEvent_Bond.png"
    },
    "11001": {
        "id": "11001",
        "name": "Estátua",
        "type": "Ocorrência",
        "image": "image/simulated_event/PicRogueEvent_Normal.png"
    },
    "11101": {
        "id": "11101",
        "name": "Ninho de Inseto",
        "type": "Ocorrência",
        "image": "image/simulated_event/PicRogueEvent_Normal.png"
    },
    "11201": {
        "id": "11201",
        "name": "Ruan Mei",
        "type": "Ocorrência",
        "image": "image/simulated_event/PicRogueEvent_Bonus.png"
    },
    "11301": {
        "id": "11301",
        "name": "Os Três Porquinhos",
        "type": "Ocorrência",
        "image": "image/simulated_event/PicRogueEvent_ThreePig.png"
    },
    "11401": {
        "id": "11401",
        "name": "Escuridão Infinita",
        "type": "Ocorrência",
        "image": "image/simulated_event/PicRogueEvent_Normal.png"
    },
    "11501": {
        "id": "11501",
        "name": "Os Arquitetos",
        "type": "Ocorrência",
        "image": "image/simulated_event/PicRogueEvent_Normal.png"
    },
    "11601": {
        "id": "11601",
        "name": "Acendedor do Autoaniquilador",
        "type": "Ocorrência",
        "image": "image/simulated_event/PicRogueEvent_Normal.png"
    },
    "11701": {
        "id": "11701",
        "name": "Comerciante Cósmico (I)",
        "type": "Ocorrência",
        "image": "image/simulated_event/PicRogueEvent_profiteer.png"
    },
    "11702": {
        "id": "11702",
        "name": "Golpe Cósmico (II)",
        "type": "Ocorrência",
        "image": "image/simulated_event/PicRogueEvent_profiteer.png"
    },
    "11703": {
        "id": "11703",
        "name": "Altruísta Cósmico (III)",
        "type": "Ocorrência",
        "image": "image/simulated_event/PicRogueEvent_profiteer.png"
    },
    "11801": {
        "id": "11801",
        "name": "Sonho de Fuga Social",
        "type": "Ocorrência",
        "image": "image/simulated_event/PicRogueEvent_Normal.png"
    },
    "11901": {
        "id": "11901",
        "name": "Saleo (I)",
        "type": "Ocorrência",
        "image": "image/simulated_event/PicRogueEvent_Twin.png"
    },
    "11902": {
        "id": "11902",
        "name": "Sal (II)",
        "type": "Ocorrência",
        "image": "image/simulated_event/PicRogueEvent_Twin.png"
    },
    "11903": {
        "id": "11903",
        "name": "Leo (III)",
        "type": "Ocorrência",
        "image": "image/simulated_event/PicRogueEvent_Twin.png"
    },
    "12001": {
        "id": "12001",
        "name": "Caçador de Recompensas",
        "type": "Ocorrência",
        "image": "image/simulated_event/PicRogueEvent_Normal.png"
    },
    "12101": {
        "id": "12101",
        "name": "Implementação de Erro",
        "type": "Ocorrência",
        "image": "image/simulated_event/PicRogueEvent_Normal.png"
    },
    "13301": {
        "id": "13301",
        "name": "Nós Somos Caubóis",
        "type": "Ocorrência",
        "image": "image/simulated_event/PicRogueEvent_Battle.png"
    },
    "13302": {
        "id": "13302",
        "name": "Nós Somos Caubóis",
        "type": "Ocorrência",
        "image": "image/simulated_event/PicRogueEvent_Battle.png"
    },
    "13401": {
        "id": "13401",
        "name": "Pedra, Papel, Tesoura",
        "type": "Ocorrência",
        "image": "image/simulated_event/PicRogueEvent_Battle.png"
    },
    "13402": {
        "id": "13402",
        "name": "Pedra, Papel, Tesoura",
        "type": "Ocorrência",
        "image": "image/simulated_event/PicRogueEvent_Battle.png"
    },
    "13501": {
        "id": "13501",
        "name": "Nildis",
        "type": "Ocorrência",
        "image": "image/simulated_event/PicRogueEvent_Normal.png"
    },
    "13502": {
        "id": "13502",
        "name": "Nildis",
        "type": "Ocorrência",
        "image": "image/simulated_event/PicRogueEvent_Normal.png"
    },
    "13503": {
        "id": "13503",
        "name": "Nildis",
        "type": "Ocorrência",
        "image": "image/simulated_event/PicRogueEvent_Normal.png"
    },
    "13601": {
        "id": "13601",
        "name": "Taverna",
        "type": "Encontro",
        "image": "image/simulated_event/PicRogueEvent_Battle.png"
    },
    "13602": {
        "id": "13602",
        "name": "Taverna",
        "type": "Encontro",
        "image": "image/simulated_event/PicRogueEvent_Battle.png"
    },
    "13603": {
        "id": "13603",
        "name": "Taverna",
        "type": "Encontro",
        "image": "image/simulated_event/PicRogueEvent_Battle.png"
    },
    "13701": {
        "id": "13701",
        "name": "Lorde Demônio Cíclico",
        "type": "Encontro",
        "image": "image/simulated_event/PicRogueEvent_Battle.png"
    },
    "13702": {
        "id": "13702",
        "name": "Lorde Demônio Cíclico",
        "type": "Encontro",
        "image": "image/simulated_event/PicRogueEvent_Battle.png"
    },
    "13703": {
        "id": "13703",
        "name": "Lorde Demônio Cíclico",
        "type": "Encontro",
        "image": "image/simulated_event/PicRogueEvent_Battle.png"
    },
    "13704": {
        "id": "13704",
        "name": "Lorde Demônio Cíclico",
        "type": "Encontro",
        "image": "image/simulated_event/PicRogueEvent_Battle.png"
    },
    "13705": {
        "id": "13705",
        "name": "Lorde Demônio Cíclico",
        "type": "Encontro",
        "image": "image/simulated_event/PicRogueEvent_Battle.png"
    },
    "13801": {
        "id": "13801",
        "name": "Vamos Trocar Presentes",
        "type": "Acordo",
        "image": "image/simulated_event/PicRogueEvent_Trade.png"
    },
    "13901": {
        "id": "13901",
        "name": "Faça um Desejo",
        "type": "Acordo",
        "image": "image/simulated_event/PicRogueEvent_Trade.png"
    },
    "14001": {
        "id": "14001",
        "name": "Terminal de Vendas de Robôs",
        "type": "Acordo",
        "image": "image/simulated_event/PicRogueEvent_Trade.png"
    },
    "110003": {
        "id": "110003",
        "name": "Loja de Curios da Herta",
        "type": "Transação",
        "image": "image/simulated_event/HoshinoKami_Herta.png"
    },
    "110004": {
        "id": "110004",
        "name": "Loja de Bênçãos do Screwllum",
        "type": "Transação",
        "image": "image/simulated_event/HoshinoKami_Herta3.png"
    },
    "110005": {
        "id": "110005",
        "name": "Loja da Herta",
        "type": "Transação",
        "image": "image/simulated_event/HoshinoKami_Herta.png"
    },
    "110006": {
        "id": "110006",
        "name": "Loja do Screwllum",
        "type": "Transação",
        "image": "image/simulated_event/HoshinoKami_Herta3.png"
    },
    "110007": {
        "id": "110007",
        "name": "Loja de Equações da Ruan Mei",
        "type": "Transação",
        "image": "image/simulated_event/HoshinoKami_Herta2.png"
    },
    "110101": {
        "id": "110101",
        "name": "Mineradores Nômades",
        "type": "Ocorrência",
        "image": "image/simulated_event/PicRogueEvent_Normal.png"
    },
    "110201": {
        "id": "110201",
        "name": "Ficciologistas da História",
        "type": "Ocorrência",
        "image": "image/simulated_event/PicRogueEvent_Historian.png"
    },
    "110301": {
        "id": "110301",
        "name": "Jim Hulk e Jim Hall",
        "type": "Ocorrência",
        "image": "image/simulated_event/PicRogueEvent_Normal.png"
    },
    "110401": {
        "id": "110401",
        "name": "Canal de Compras",
        "type": "Ocorrência",
        "image": "image/simulated_event/PicRogueEvent_Normal.png"
    },
    "110501": {
        "id": "110501",
        "name": "Os Cremadores",
        "type": "Ocorrência",
        "image": "image/simulated_event/PicRogueEvent_Normal.png"
    },
    "110601": {
        "id": "110601",
        "name": "Artes Interativas",
        "type": "Ocorrência",
        "image": "image/simulated_event/PicRogueEvent_Normal.png"
    },
    "110701": {
        "id": "110701",
        "name": "Mundo Pixelado",
        "type": "Ocorrência",
        "image": "image/simulated_event/PicRogueEvent_Pixel.png"
    },
    "110801": {
        "id": "110801",
        "name": "Pelúcia de Aha",
        "type": "Ocorrência",
        "image": "image/simulated_event/PicRogueEvent_Toy.png"
    },
    "110901": {
        "id": "110901",
        "name": "Dispensador de Promissórias",
        "type": "Ocorrência",
        "image": "image/simulated_event/PicRogueEvent_Bond.png"
    },
    "111001": {
        "id": "111001",
        "name": "Estátua",
        "type": "Ocorrência",
        "image": "image/simulated_event/PicRogueEvent_Normal.png"
    },
    "111101": {
        "id": "111101",
        "name": "Ninho de Inseto",
        "type": "Ocorrência",
        "image": "image/simulated_event/PicRogueEvent_Normal.png"
    },
    "111201": {
        "id": "111201",
        "name": "Ruan Mei",
        "type": "Ocorrência",
        "image": "image/simulated_event/PicRogueEvent_Bonus.png"
    },
    "111301": {
        "id": "111301",
        "name": "Os Três Porquinhos",
        "type": "Ocorrência",
        "image": "image/simulated_event/PicRogueEvent_ThreePig.png"
    },
    "111401": {
        "id": "111401",
        "name": "Escuridão Infinita",
        "type": "Ocorrência",
        "image": "image/simulated_event/PicRogueEvent_Normal.png"
    },
    "111501": {
        "id": "111501",
        "name": "Os Arquitetos",
        "type": "Ocorrência",
        "image": "image/simulated_event/PicRogueEvent_Normal.png"
    },
    "111601": {
        "id": "111601",
        "name": "Acendedor do Autoaniquilador",
        "type": "Ocorrência",
        "image": "image/simulated_event/PicRogueEvent_Normal.png"
    },
    "111701": {
        "id": "111701",
        "name": "Comerciante Cósmico (I)",
        "type": "Ocorrência",
        "image": "image/simulated_event/PicRogueEvent_profiteer.png"
    },
    "111702": {
        "id": "111702",
        "name": "Golpe Cósmico (II)",
        "type": "Ocorrência",
        "image": "image/simulated_event/PicRogueEvent_profiteer.png"
    },
    "111703": {
        "id": "111703",
        "name": "Altruísta Cósmico (III)",
        "type": "Ocorrência",
        "image": "image/simulated_event/PicRogueEvent_profiteer.png"
    },
    "111801": {
        "id": "111801",
        "name": "Sonho de Fuga Social",
        "type": "Ocorrência",
        "image": "image/simulated_event/PicRogueEvent_Normal.png"
    },
    "111901": {
        "id": "111901",
        "name": "Saleo (I)",
        "type": "Ocorrência",
        "image": "image/simulated_event/PicRogueEvent_Twin.png"
    },
    "111902": {
        "id": "111902",
        "name": "Sal (II)",
        "type": "Ocorrência",
        "image": "image/simulated_event/PicRogueEvent_Twin.png"
    },
    "111903": {
        "id": "111903",
        "name": "Leo (III)",
        "type": "Ocorrência",
        "image": "image/simulated_event/PicRogueEvent_Twin.png"
    },
    "112001": {
        "id": "112001",
        "name": "Caçador de Recompensas",
        "type": "Ocorrência",
        "image": "image/simulated_event/PicRogueEvent_Normal.png"
    },
    "112101": {
        "id": "112101",
        "name": "Implementação de Erro",
        "type": "Ocorrência",
        "image": "image/simulated_event/PicRogueEvent_Normal.png"
    },
    "112201": {
        "id": "112201",
        "name": "Cavaleiros da Beleza ao Resgate",
        "type": "Ocorrência",
        "image": "image/simulated_event/PicRogueEvent_1.png"
    },
    "112301": {
        "id": "112301",
        "name": "Crescendo Cósmico",
        "type": "Ocorrência",
        "image": "image/simulated_event/PicRogueEvent_Normal.png"
    },
    "112401": {
        "id": "112401",
        "name": "Sociedade de Gênios #55 Yu Qingtu",
        "type": "Ocorrência",
        "image": "image/simulated_event/PicRogueEvent_7.png"
    },
    "112501": {
        "id": "112501",
        "name": "Horda de Feras: Catástrofe Voraz",
        "type": "Ocorrência",
        "image": "image/simulated_event/PicRogueEvent_3.png"
    },
    "112601": {
        "id": "112601",
        "name": "Reparador de Curios",
        "type": "Ocorrência",
        "image": "image/simulated_event/PicRogueEvent_Toy.png"
    },
    "112701": {
        "id": "112701",
        "name": "Trenó do Apresentador",
        "type": "Ocorrência",
        "image": "image/simulated_event/PicRogueEvent_profiteer.png"
    },
    "112801": {
        "id": "112801",
        "name": "A Experiência de Loteria Dupla",
        "type": "Ocorrência",
        "image": "image/simulated_event/PicRogueEvent_Bond.png"
    },
    "112901": {
        "id": "112901",
        "name": "Ruan Mei (II)",
        "type": "Ocorrência",
        "image": "image/simulated_event/PicRogueEvent_5.png"
    },
    "113001": {
        "id": "113001",
        "name": "O Grande Desafio Perfeito!",
        "type": "Ocorrência",
        "image": "image/simulated_event/PicRogueEvent_Toy.png"
    },
    "113301": {
        "id": "113301",
        "name": "Nós Somos Caubóis",
        "type": "Ocorrência",
        "image": "image/simulated_event/PicRogueEvent_Battle.png"
    },
    "113302": {
        "id": "113302",
        "name": "Nós Somos Caubóis",
        "type": "Ocorrência",
        "image": "image/simulated_event/PicRogueEvent_Battle.png"
    },
    "113401": {
        "id": "113401",
        "name": "Pedra, Papel, Tesoura",
        "type": "Ocorrência",
        "image": "image/simulated_event/PicRogueEvent_Battle.png"
    },
    "113402": {
        "id": "113402",
        "name": "Pedra, Papel, Tesoura",
        "type": "Ocorrência",
        "image": "image/simulated_event/PicRogueEvent_Battle.png"
    },
    "113501": {
        "id": "113501",
        "name": "Nildis",
        "type": "Ocorrência",
        "image": "image/simulated_event/PicRogueEvent_Normal.png"
    },
    "113502": {
        "id": "113502",
        "name": "Nildis",
        "type": "Ocorrência",
        "image": "image/simulated_event/PicRogueEvent_Normal.png"
    },
    "113503": {
        "id": "113503",
        "name": "Nildis",
        "type": "Ocorrência",
        "image": "image/simulated_event/PicRogueEvent_Normal.png"
    },
    "113601": {
        "id": "113601",
        "name": "Taverna",
        "type": "Ocorrência",
        "image": "image/simulated_event/PicRogueEvent_Battle.png"
    },
    "113602": {
        "id": "113602",
        "name": "Taverna",
        "type": "Ocorrência",
        "image": "image/simulated_event/PicRogueEvent_Battle.png"
    },
    "113603": {
        "id": "113603",
        "name": "Taverna",
        "type": "Ocorrência",
        "image": "image/simulated_event/PicRogueEvent_Battle.png"
    },
    "113701": {
        "id": "113701",
        "name": "Lorde Demônio Periódico",
        "type": "Ocorrência",
        "image": "image/simulated_event/PicRogueEvent_Battle.png"
    },
    "113702": {
        "id": "113702",
        "name": "Lorde Demônio Periódico",
        "type": "Ocorrência",
        "image": "image/simulated_event/PicRogueEvent_Battle.png"
    },
    "113703": {
        "id": "113703",
        "name": "Lorde Demônio Periódico",
        "type": "Ocorrência",
        "image": "image/simulated_event/PicRogueEvent_Battle.png"
    },
    "113704": {
        "id": "113704",
        "name": "Lorde Demônio Periódico",
        "type": "Ocorrência",
        "image": "image/simulated_event/PicRogueEvent_Battle.png"
    },
    "113705": {
        "id": "113705",
        "name": "Lorde Demônio Periódico",
        "type": "Ocorrência",
        "image": "image/simulated_event/PicRogueEvent_Battle.png"
    },
    "113801": {
        "id": "113801",
        "name": "Vamos Trocar Presentes",
        "type": "Ocorrência",
        "image": "image/simulated_event/PicRogueEvent_Trade.png"
    },
    "113901": {
        "id": "113901",
        "name": "Faça um Desejo",
        "type": "Ocorrência",
        "image": "image/simulated_event/PicRogueEvent_Trade.png"
    },
    "114001": {
        "id": "114001",
        "name": "Terminal de Vendas de Robôs",
        "type": "Ocorrência",
        "image": "image/simulated_event/PicRogueEvent_Trade.png"
    },
    "114101": {
        "id": "114101",
        "name": "O Fanático dos Relógios Cuco (I)",
        "type": "Ocorrência",
        "image": "image/simulated_event/PicRogueEvent_Twin.png"
    },
    "114102": {
        "id": "114102",
        "name": "O Fanático dos Relógios Cuco (II)",
        "type": "Ocorrência",
        "image": "image/simulated_event/PicRogueEvent_Twin.png"
    },
    "114103": {
        "id": "114103",
        "name": "O Fanático dos Relógios Cuco (III)",
        "type": "Ocorrência",
        "image": "image/simulated_event/PicRogueEvent_Twin.png"
    },
    "114201": {
        "id": "114201",
        "name": "A Saga de Promoção da CPI (I)",
        "type": "Ocorrência",
        "image": "image/simulated_event/PicRogueEvent_Bond.png"
    },
    "114202": {
        "id": "114202",
        "name": "A Saga de Promoção da CPI (II)",
        "type": "Ocorrência",
        "image": "image/simulated_event/PicRogueEvent_Bond.png"
    },
    "114203": {
        "id": "114203",
        "name": "A Saga de Promoção da CPI (III)",
        "type": "Ocorrência",
        "image": "image/simulated_event/PicRogueEvent_Bond.png"
    },
    "114204": {
        "id": "114204",
        "name": "A Saga de Promoção da CPI (IV)",
        "type": "Ocorrência",
        "image": "image/simulated_event/PicRogueEvent_Bond.png"
    },
    "114301": {
        "id": "114301",
        "name": "Dindin! Serviços Bancários da CPI (I)",
        "type": "Ocorrência",
        "image": "image/simulated_event/PicRogueEvent_Bond.png"
    },
    "114302": {
        "id": "114302",
        "name": "Dindin! Serviços Bancários da CPI (II)",
        "type": "Ocorrência",
        "image": "image/simulated_event/PicRogueEvent_Bond.png"
    },
    "114401": {
        "id": "114401",
        "name": "Solidão, Insetos da Beleza Cósmicos, Universo Simulado (I)",
        "type": "Ocorrência",
        "image": "image/simulated_event/PicRogueEvent_2.png"
    },
    "114402": {
        "id": "114402",
        "name": "Solidão, Insetos da Beleza Cósmicos, Universo Simulado (II)",
        "type": "Ocorrência",
        "image": "image/simulated_event/PicRogueEvent_2.png"
    },
    "114501": {
        "id": "114501",
        "name": "Catador de Lixo Primoroso",
        "type": "Ocorrência",
        "image": "image/simulated_event/PicRogueEvent_Normal.png"
    },
    "114601": {
        "id": "114601",
        "name": "Majestade da Areia: Tayzzyronth (I)",
        "type": "Segredos",
        "image": "image/simulated_event/RoguePicEventDLC_01.png"
    },
    "114701": {
        "id": "114701",
        "name": "Majestade da Areia: Tayzzyronth (II)",
        "type": "Segredos",
        "image": "image/simulated_event/RoguePicEventDLC_01.png"
    },
    "114801": {
        "id": "114801",
        "name": "Majestade da Areia: Tayzzyronth (III)",
        "type": "Segredos",
        "image": "image/simulated_event/RoguePicEventDLC_01.png"
    },
    "114901": {
        "id": "114901",
        "name": "Majestade da Areia: Tayzzyronth (IV)",
        "type": "Segredos",
        "image": "image/simulated_event/RoguePicEventDLC_01.png"
    },
    "115001": {
        "id": "115001",
        "name": "Majestade da Areia: Tayzzyronth (V)",
        "type": "Segredos",
        "image": "image/simulated_event/RoguePicEventDLC_01.png"
    },
    "115101": {
        "id": "115101",
        "name": "Majestade da Areia: Tayzzyronth (VI)",
        "type": "Segredos",
        "image": "image/simulated_event/RoguePicEventDLC_01.png"
    },
    "115201": {
        "id": "115201",
        "name": "Majestade da Areia: Tayzzyronth (VII)",
        "type": "Segredos",
        "image": "image/simulated_event/RoguePicEventDLC_01.png"
    },
    "115301": {
        "id": "115301",
        "name": "Majestade da Areia: Tayzzyronth (VIII)",
        "type": "Segredos",
        "image": "image/simulated_event/RoguePicEventDLC_01.png"
    },
    "115401": {
        "id": "115401",
        "name": "Majestade da Areia: Tayzzyronth (IX)",
        "type": "Segredos",
        "image": "image/simulated_event/RoguePicEventDLC_01.png"
    },
    "115501": {
        "id": "115501",
        "name": "Sistema Lepisma: Saga do Massacre (I)",
        "type": "Segredos",
        "image": "image/simulated_event/RoguePicEventDLC_02.png"
    },
    "115601": {
        "id": "115601",
        "name": "Sistema Lepisma: Saga do Massacre (II)",
        "type": "Segredos",
        "image": "image/simulated_event/RoguePicEventDLC_02.png"
    },
    "115701": {
        "id": "115701",
        "name": "Sistema Lepisma: Saga do Massacre (III)",
        "type": "Segredos",
        "image": "image/simulated_event/RoguePicEventDLC_02.png"
    },
    "115801": {
        "id": "115801",
        "name": "Sistema Lepisma: Saga do Massacre (IV)",
        "type": "Segredos",
        "image": "image/simulated_event/RoguePicEventDLC_02.png"
    },
    "115901": {
        "id": "115901",
        "name": "Sistema Lepisma: Saga do Massacre (V)",
        "type": "Segredos",
        "image": "image/simulated_event/RoguePicEventDLC_02.png"
    },
    "116001": {
        "id": "116001",
        "name": "Sistema Lepisma: Saga do Massacre (VI)",
        "type": "Segredos",
        "image": "image/simulated_event/RoguePicEventDLC_02.png"
    },
    "116101": {
        "id": "116101",
        "name": "Caçador de Recompensas: Crônica da Limpeza Carmesim (I)",
        "type": "Segredos",
        "image": "image/simulated_event/RoguePicEventDLC_02.png"
    },
    "116201": {
        "id": "116201",
        "name": "Caçador de Recompensas: Crônica da Limpeza Carmesim (II)",
        "type": "Segredos",
        "image": "image/simulated_event/RoguePicEventDLC_02.png"
    },
    "116301": {
        "id": "116301",
        "name": "Caçador de Recompensas: Crônica da Limpeza Carmesim (III)",
        "type": "Segredos",
        "image": "image/simulated_event/RoguePicEventDLC_02.png"
    },
    "116401": {
        "id": "116401",
        "name": "Caçador de Recompensas: Crônica da Limpeza Carmesim (IV)",
        "type": "Segredos",
        "image": "image/simulated_event/RoguePicEventDLC_02.png"
    },
    "116501": {
        "id": "116501",
        "name": "Caçador de Recompensas: Crônica da Limpeza Carmesim (V)",
        "type": "Segredos",
        "image": "image/simulated_event/RoguePicEventDLC_02.png"
    },
    "116601": {
        "id": "116601",
        "name": "Caçador de Recompensas: Crônica da Limpeza Carmesim (VI)",
        "type": "Segredos",
        "image": "image/simulated_event/RoguePicEventDLC_02.png"
    },
    "116701": {
        "id": "116701",
        "name": "Tragédia e Insetos: O Declínio das Estrelas (I)",
        "type": "Segredos",
        "image": "image/simulated_event/RoguePicEventDLC_03.png"
    },
    "116801": {
        "id": "116801",
        "name": "Tragédia e Insetos: O Declínio das Estrelas (II)",
        "type": "Segredos",
        "image": "image/simulated_event/RoguePicEventDLC_03.png"
    },
    "116901": {
        "id": "116901",
        "name": "Tragédia e Insetos: O Declínio das Estrelas (III)",
        "type": "Segredos",
        "image": "image/simulated_event/RoguePicEventDLC_03.png"
    },
    "117001": {
        "id": "117001",
        "name": "Tragédia e Insetos: O Declínio das Estrelas (IV)",
        "type": "Segredos",
        "image": "image/simulated_event/RoguePicEventDLC_03.png"
    },
    "117101": {
        "id": "117101",
        "name": "Tragédia e Insetos: O Declínio das Estrelas (V)",
        "type": "Segredos",
        "image": "image/simulated_event/RoguePicEventDLC_03.png"
    },
    "117201": {
        "id": "117201",
        "name": "Tragédia e Insetos: O Declínio das Estrelas (VI)",
        "type": "Segredos",
        "image": "image/simulated_event/RoguePicEventDLC_03.png"
    },
    "117301": {
        "id": "117301",
        "name": "Sociedade de Gênios: Experimentos Regulares (I)",
        "type": "Segredos",
        "image": "image/simulated_event/RoguePicEventDLC_01.png"
    },
    "117401": {
        "id": "117401",
        "name": "Sociedade de Gênios: Experimentos Regulares (II)",
        "type": "Segredos",
        "image": "image/simulated_event/RoguePicEventDLC_01.png"
    },
    "117501": {
        "id": "117501",
        "name": "Sociedade de Gênios: Experimentos Regulares (III)",
        "type": "Segredos",
        "image": "image/simulated_event/RoguePicEventDLC_01.png"
    },
    "117601": {
        "id": "117601",
        "name": "Gondola: Deuses Assistentes! (I)",
        "type": "Segredos",
        "image": "image/simulated_event/RoguePicEventDLC_05.png"
    },
    "117701": {
        "id": "117701",
        "name": "Gondola: Deuses Assistentes! (II)",
        "type": "Segredos",
        "image": "image/simulated_event/RoguePicEventDLC_05.png"
    },
    "117801": {
        "id": "117801",
        "name": "Gondola: Deuses Assistentes! (III)",
        "type": "Segredos",
        "image": "image/simulated_event/RoguePicEventDLC_05.png"
    },
    "117901": {
        "id": "117901",
        "name": "Gondola: Deuses Assistentes! (IV)",
        "type": "Segredos",
        "image": "image/simulated_event/RoguePicEventDLC_05.png"
    },
    "118001": {
        "id": "118001",
        "name": "Gondola: Deuses Assistentes! (V)",
        "type": "Segredos",
        "image": "image/simulated_event/RoguePicEventDLC_05.png"
    },
    "118101": {
        "id": "118101",
        "name": "Gondola: Deuses Assistentes! (VI)",
        "type": "Segredos",
        "image": "image/simulated_event/RoguePicEventDLC_05.png"
    },
    "118201": {
        "id": "118201",
        "name": "Coro Além do Céu: Arquivos da Anomalia (I)",
        "type": "Segredos",
        "image": "image/simulated_event/RoguePicEventDLC_04.png"
    },
    "118301": {
        "id": "118301",
        "name": "Coro Além do Céu: Arquivos da Anomalia (II)",
        "type": "Segredos",
        "image": "image/simulated_event/RoguePicEventDLC_04.png"
    },
    "118401": {
        "id": "118401",
        "name": "Coro Além do Céu: Arquivos da Anomalia (III)",
        "type": "Segredos",
        "image": "image/simulated_event/RoguePicEventDLC_04.png"
    },
    "118501": {
        "id": "118501",
        "name": "Os Arquitetos: Histórias da Fortificação (I)",
        "type": "Segredos",
        "image": "image/simulated_event/RoguePicEventDLC_06.png"
    },
    "118601": {
        "id": "118601",
        "name": "Os Arquitetos: Histórias da Fortificação (II)",
        "type": "Segredos",
        "image": "image/simulated_event/RoguePicEventDLC_06.png"
    },
    "118701": {
        "id": "118701",
        "name": "Os Arquitetos: Histórias da Fortificação (III)",
        "type": "Segredos",
        "image": "image/simulated_event/RoguePicEventDLC_06.png"
    },
    "118801": {
        "id": "118801",
        "name": "Enxame: Soberano Adormecido (Primeiro Pretoriano)",
        "type": "O Enxame",
        "image": "image/simulated_event/PicRogueEvent_4.png"
    },
    "118802": {
        "id": "118802",
        "name": "Enxame: Soberano Adormecido (Segundo Pretoriano)",
        "type": "O Enxame",
        "image": "image/simulated_event/PicRogueEvent_4.png"
    },
    "118803": {
        "id": "118803",
        "name": "Enxame: Soberano Adormecido (Terceiro Pretoriano)",
        "type": "O Enxame",
        "image": "image/simulated_event/PicRogueEvent_4.png"
    },
    "118901": {
        "id": "118901",
        "name": "Propagação: Soberano Adormecido (Primeiro Pretoriano)",
        "type": "O Enxame",
        "image": "image/simulated_event/PicRogueEvent_4.png"
    },
    "118902": {
        "id": "118902",
        "name": "Propagação: Soberano Adormecido (Segundo Pretoriano)",
        "type": "O Enxame",
        "image": "image/simulated_event/PicRogueEvent_4.png"
    },
    "118903": {
        "id": "118903",
        "name": "Propagação: Soberano Adormecido (Terceiro Pretoriano)",
        "type": "O Enxame",
        "image": "image/simulated_event/PicRogueEvent_4.png"
    },
    "119001": {
        "id": "119001",
        "name": "Enxame: Exploração de Ninho (Primeiro Pretoriano)",
        "type": "O Enxame",
        "image": "image/simulated_event/PicRogueEvent_4.png"
    },
    "119002": {
        "id": "119002",
        "name": "Enxame: Exploração de Ninho (Segundo Pretoriano)",
        "type": "O Enxame",
        "image": "image/simulated_event/PicRogueEvent_4.png"
    },
    "119003": {
        "id": "119003",
        "name": "Enxame: Exploração de Ninho (Terceiro Pretoriano)",
        "type": "O Enxame",
        "image": "image/simulated_event/PicRogueEvent_4.png"
    },
    "119101": {
        "id": "119101",
        "name": "Propagação: Exploração de Ninho (Primeiro Pretoriano)",
        "type": "O Enxame",
        "image": "image/simulated_event/PicRogueEvent_4.png"
    },
    "119102": {
        "id": "119102",
        "name": "Propagação: Exploração de Ninho (Segundo Pretoriano)",
        "type": "O Enxame",
        "image": "image/simulated_event/PicRogueEvent_4.png"
    },
    "119201": {
        "id": "119201",
        "name": "Enxame: Mente do Domínio (Primeiro Pretoriano)",
        "type": "O Enxame",
        "image": "image/simulated_event/PicRogueEvent_4.png"
    },
    "119202": {
        "id": "119202",
        "name": "Enxame: Mente do Domínio (Segundo Pretoriano)",
        "type": "O Enxame",
        "image": "image/simulated_event/PicRogueEvent_4.png"
    },
    "119203": {
        "id": "119203",
        "name": "Enxame: Mente do Domínio (Terceiro Pretoriano)",
        "type": "O Enxame",
        "image": "image/simulated_event/PicRogueEvent_4.png"
    },
    "119301": {
        "id": "119301",
        "name": "Vislumbres da Dançarina Universal",
        "type": "Ocorrência",
        "image": "image/simulated_event/PicRogueEvent_profiteer.png"
    },
    "119401": {
        "id": "119401",
        "name": "Mundo Pixelado: Estágio Oculto",
        "type": "Ocorrência",
        "image": "image/simulated_event/PicRogueEvent_Pixel.png"
    },
    "119501": {
        "id": "119501",
        "name": "Espelho da Transcendência",
        "type": "Ocorrência",
        "image": "image/simulated_event/PicRogueEvent_Normal.png"
    },
    "119502": {
        "id": "119502",
        "name": "Espelho da Transcendência",
        "type": "Ocorrência",
        "image": "image/simulated_event/PicRogueEvent_Normal.png"
    },
    "119503": {
        "id": "119503",
        "name": "Espelho da Transcendência",
        "type": "Ocorrência",
        "image": "image/simulated_event/PicRogueEvent_Normal.png"
    },
    "119504": {
        "id": "119504",
        "name": "Espelho da Transcendência",
        "type": "Ocorrência",
        "image": "image/simulated_event/PicRogueEvent_Normal.png"
    },
    "219701": {
        "id": "219701",
        "name": "Ruan Mei (Infinito)",
        "type": "Ocorrência",
        "image": "image/simulated_event/PicRogueEvent_Bonus.png"
    },
    "320101": {
        "id": "320101",
        "name": "Cidade Mecânica \"Salão de Cabeleireiro Cogito\" - Screwllita",
        "type": "Ocorrência",
        "image": "image/simulated_event/PicRogueEvent_10.png"
    },
    "320201": {
        "id": "320201",
        "name": "Cidade Mecânica \"Salão de Cabeleireiro Cogito\" - Guilda de Intelectuais",
        "type": "Ocorrência",
        "image": "image/simulated_event/PicRogueEvent_8.png"
    },
    "320301": {
        "id": "320301",
        "name": "Cidade Mecânica \"Salão de Cabeleireiro Cogito\" - Sociedade de Gênios",
        "type": "Ocorrência",
        "image": "image/simulated_event/PicRogueEvent_9.png"
    },
    "320401": {
        "id": "320401",
        "name": "Hacker de Curio",
        "type": "Ocorrência",
        "image": "image/simulated_event/PicRogueEvent_Normal.png"
    },
    "320501": {
        "id": "320501",
        "name": "Máquina de Fabricação de Cera Seladora",
        "type": "Ocorrência",
        "image": "image/simulated_event/PicRogueEvent_Normal.png"
    },
    "320601": {
        "id": "320601",
        "name": "Dispositivo de Investimento da Paz Interastral",
        "type": "Ocorrência",
        "image": "image/simulated_event/PicRogueEvent_Bond.png"
    },
    "320701": {
        "id": "320701",
        "name": "Shopping da Filial Mecânica da Paz Interastral (I)",
        "type": "Ocorrência",
        "image": "image/simulated_event/PicRogueEvent_Bond.png"
    },
    "320801": {
        "id": "320801",
        "name": "Shopping da Filial Mecânica da Paz Interastral (II)",
        "type": "Ocorrência",
        "image": "image/simulated_event/PicRogueEvent_Bond.png"
    },
    "320901": {
        "id": "320901",
        "name": "Código de Trapaça (I)",
        "type": "Ocorrência",
        "image": "image/simulated_event/PicRogueEvent_Normal.png"
    },
    "320902": {
        "id": "320902",
        "name": "Código de Trapaça (II)",
        "type": "Ocorrência",
        "image": "image/simulated_event/PicRogueEvent_Normal.png"
    },
    "410101": {
        "id": "410101",
        "name": "Mineradores Nômades",
        "type": "Ocorrência",
        "image": "image/simulated_event/PicRogueEvent_Normal.png"
    },
    "410201": {
        "id": "410201",
        "name": "Ficciologistas da História",
        "type": "Ocorrência",
        "image": "image/simulated_event/PicRogueEvent_Historian.png"
    },
    "410301": {
        "id": "410301",
        "name": "Jim Hulk e Jim Hall",
        "type": "Ocorrência",
        "image": "image/simulated_event/PicRogueEvent_Normal.png"
    },
    "410401": {
        "id": "410401",
        "name": "Canal de Compras",
        "type": "Ocorrência",
        "image": "image/simulated_event/PicRogueEvent_Normal.png"
    },
    "410501": {
        "id": "410501",
        "name": "Os Cremadores",
        "type": "Ocorrência",
        "image": "image/simulated_event/PicRogueEvent_Normal.png"
    },
    "410601": {
        "id": "410601",
        "name": "Artes Interativas",
        "type": "Ocorrência",
        "image": "image/simulated_event/PicRogueEvent_Normal.png"
    },
    "410701": {
        "id": "410701",
        "name": "Mundo Pixelado",
        "type": "Ocorrência",
        "image": "image/simulated_event/PicRogueEvent_Pixel.png"
    },
    "410801": {
        "id": "410801",
        "name": "Pelúcia de Aha",
        "type": "Ocorrência",
        "image": "image/simulated_event/PicRogueEvent_Toy.png"
    },
    "410901": {
        "id": "410901",
        "name": "Dispensador de Promissórias",
        "type": "Ocorrência",
        "image": "image/simulated_event/PicRogueEvent_Bond.png"
    },
    "411001": {
        "id": "411001",
        "name": "Estátua",
        "type": "Ocorrência",
        "image": "image/simulated_event/PicRogueEvent_Normal.png"
    },
    "411101": {
        "id": "411101",
        "name": "Ninho de Inseto",
        "type": "Ocorrência",
        "image": "image/simulated_event/PicRogueEvent_Normal.png"
    },
    "411201": {
        "id": "411201",
        "name": "Ruan Mei",
        "type": "Ocorrência",
        "image": "image/simulated_event/PicRogueEvent_Bonus.png"
    },
    "411301": {
        "id": "411301",
        "name": "Os Três Porquinhos",
        "type": "Ocorrência",
        "image": "image/simulated_event/PicRogueEvent_ThreePig.png"
    },
    "411401": {
        "id": "411401",
        "name": "Escuridão Infinita",
        "type": "Ocorrência",
        "image": "image/simulated_event/PicRogueEvent_Normal.png"
    },
    "411501": {
        "id": "411501",
        "name": "Os Arquitetos",
        "type": "Ocorrência",
        "image": "image/simulated_event/PicRogueEvent_Normal.png"
    },
    "411601": {
        "id": "411601",
        "name": "Acendedor do Autoaniquilador",
        "type": "Ocorrência",
        "image": "image/simulated_event/PicRogueEvent_Normal.png"
    },
    "411701": {
        "id": "411701",
        "name": "Comerciante Cósmico (I)",
        "type": "Ocorrência",
        "image": "image/simulated_event/PicRogueEvent_profiteer.png"
    },
    "411702": {
        "id": "411702",
        "name": "Golpe Cósmico (II)",
        "type": "Ocorrência",
        "image": "image/simulated_event/PicRogueEvent_profiteer.png"
    },
    "411703": {
        "id": "411703",
        "name": "Altruísta Cósmico (III)",
        "type": "Ocorrência",
        "image": "image/simulated_event/PicRogueEvent_profiteer.png"
    },
    "411801": {
        "id": "411801",
        "name": "Sonho de Fuga Social",
        "type": "Ocorrência",
        "image": "image/simulated_event/PicRogueEvent_Normal.png"
    },
    "411901": {
        "id": "411901",
        "name": "Saleo (I)",
        "type": "Ocorrência",
        "image": "image/simulated_event/PicRogueEvent_Twin.png"
    },
    "411902": {
        "id": "411902",
        "name": "Sal (II)",
        "type": "Ocorrência",
        "image": "image/simulated_event/PicRogueEvent_Twin.png"
    },
    "411903": {
        "id": "411903",
        "name": "Leo (III)",
        "type": "Ocorrência",
        "image": "image/simulated_event/PicRogueEvent_Twin.png"
    },
    "412001": {
        "id": "412001",
        "name": "Caçador de Recompensas",
        "type": "Ocorrência",
        "image": "image/simulated_event/PicRogueEvent_Normal.png"
    },
    "412201": {
        "id": "412201",
        "name": "Cavaleiros da Beleza ao Resgate",
        "type": "Ocorrência",
        "image": "image/simulated_event/PicRogueEvent_1.png"
    },
    "412301": {
        "id": "412301",
        "name": "Crescendo Cósmico",
        "type": "Ocorrência",
        "image": "image/simulated_event/PicRogueEvent_Normal.png"
    },
    "412401": {
        "id": "412401",
        "name": "Sociedade de Gênios #55 Yu Qingtu",
        "type": "Ocorrência",
        "image": "image/simulated_event/PicRogueEvent_7.png"
    },
    "412501": {
        "id": "412501",
        "name": "Horda de Feras: Catástrofe Voraz",
        "type": "Ocorrência",
        "image": "image/simulated_event/PicRogueEvent_3.png"
    },
    "412601": {
        "id": "412601",
        "name": "Reparador de Curios",
        "type": "Ocorrência",
        "image": "image/simulated_event/PicRogueEvent_Toy.png"
    },
    "412701": {
        "id": "412701",
        "name": "Trenó do Apresentador",
        "type": "Ocorrência",
        "image": "image/simulated_event/PicRogueEvent_profiteer.png"
    },
    "412801": {
        "id": "412801",
        "name": "A Experiência de Loteria Dupla",
        "type": "Ocorrência",
        "image": "image/simulated_event/PicRogueEvent_Bond.png"
    },
    "412802": {
        "id": "412802",
        "name": "A Experiência da Super Loteria",
        "type": "Ocorrência",
        "image": "image/simulated_event/PicRogueEvent_Bond.png"
    },
    "412901": {
        "id": "412901",
        "name": "Ruan Mei (II)",
        "type": "Ocorrência",
        "image": "image/simulated_event/PicRogueEvent_5.png"
    },
    "413001": {
        "id": "413001",
        "name": "O Grande Desafio Perfeito!",
        "type": "Ocorrência",
        "image": "image/simulated_event/PicRogueEvent_Toy.png"
    },
    "413301": {
        "id": "413301",
        "name": "Nós Somos Caubóis",
        "type": "Ocorrência",
        "image": "image/simulated_event/PicRogueEvent_Battle.png"
    },
    "413401": {
        "id": "413401",
        "name": "Pedra, Papel, Tesoura",
        "type": "Ocorrência",
        "image": "image/simulated_event/PicRogueEvent_Battle.png"
    },
    "413501": {
        "id": "413501",
        "name": "Nildis",
        "type": "Ocorrência",
        "image": "image/simulated_event/PicRogueEvent_Normal.png"
    },
    "413601": {
        "id": "413601",
        "name": "Taverna",
        "type": "Ocorrência",
        "image": "image/simulated_event/PicRogueEvent_Battle.png"
    },
    "413701": {
        "id": "413701",
        "name": "Lorde Demônio Cíclico",
        "type": "Ocorrência",
        "image": "image/simulated_event/PicRogueEvent_Battle.png"
    },
    "413801": {
        "id": "413801",
        "name": "Vamos Trocar Presentes",
        "type": "Ocorrência",
        "image": "image/simulated_event/PicRogueEvent_Trade.png"
    },
    "413901": {
        "id": "413901",
        "name": "Faça um Desejo",
        "type": "Ocorrência",
        "image": "image/simulated_event/PicRogueEvent_Trade.png"
    },
    "414001": {
        "id": "414001",
        "name": "Terminal de Vendas de Robôs",
        "type": "Ocorrência",
        "image": "image/simulated_event/PicRogueEvent_Trade.png"
    },
    "414101": {
        "id": "414101",
        "name": "O Fanático dos Relógios Cuco (I)",
        "type": "Ocorrência",
        "image": "image/simulated_event/PicRogueEvent_Twin.png"
    },
    "414102": {
        "id": "414102",
        "name": "O Fanático dos Relógios Cuco (II)",
        "type": "Ocorrência",
        "image": "image/simulated_event/PicRogueEvent_Twin.png"
    },
    "414103": {
        "id": "414103",
        "name": "O Fanático dos Relógios Cuco (III)",
        "type": "Ocorrência",
        "image": "image/simulated_event/PicRogueEvent_Twin.png"
    },
    "414201": {
        "id": "414201",
        "name": "A Saga de Promoção da CPI (I)",
        "type": "Ocorrência",
        "image": "image/simulated_event/PicRogueEvent_Bond.png"
    },
    "414202": {
        "id": "414202",
        "name": "A Saga de Promoção da CPI (II)",
        "type": "Ocorrência",
        "image": "image/simulated_event/PicRogueEvent_Bond.png"
    },
    "414203": {
        "id": "414203",
        "name": "A Saga de Promoção da CPI (III)",
        "type": "Ocorrência",
        "image": "image/simulated_event/PicRogueEvent_Bond.png"
    },
    "414204": {
        "id": "414204",
        "name": "A Saga de Promoção da CPI (IV)",
        "type": "Ocorrência",
        "image": "image/simulated_event/PicRogueEvent_Bond.png"
    },
    "414301": {
        "id": "414301",
        "name": "Dindin! Serviços Bancários da CPI (I)",
        "type": "Ocorrência",
        "image": "image/simulated_event/PicRogueEvent_Bond.png"
    },
    "414302": {
        "id": "414302",
        "name": "Dindin! Serviços Bancários da CPI (II)",
        "type": "Ocorrência",
        "image": "image/simulated_event/PicRogueEvent_Bond.png"
    },
    "414401": {
        "id": "414401",
        "name": "Solidão, Insetos da Beleza Cósmicos, Universo Simulado (I)",
        "type": "Ocorrência",
        "image": "image/simulated_event/PicRogueEvent_2.png"
    },
    "414402": {
        "id": "414402",
        "name": "Solidão, Insetos da Beleza Cósmicos, Universo Simulado (II)",
        "type": "Ocorrência",
        "image": "image/simulated_event/PicRogueEvent_2.png"
    },
    "414501": {
        "id": "414501",
        "name": "Catador de Lixo Primoroso",
        "type": "Ocorrência",
        "image": "image/simulated_event/PicRogueEvent_Normal.png"
    },
    "418801": {
        "id": "418801",
        "name": "Enxame: Soberano Adormecido (Primeiro Pretoriano)",
        "type": "Ocorrência",
        "image": "image/simulated_event/PicRogueEvent_4.png"
    },
    "418802": {
        "id": "418802",
        "name": "Enxame: Soberano Adormecido (Segundo Pretoriano)",
        "type": "Ocorrência",
        "image": "image/simulated_event/PicRogueEvent_4.png"
    },
    "418803": {
        "id": "418803",
        "name": "Enxame: Soberano Adormecido (Terceiro Pretoriano)",
        "type": "Ocorrência",
        "image": "image/simulated_event/PicRogueEvent_4.png"
    },
    "419001": {
        "id": "419001",
        "name": "Enxame: Exploração de Ninho (Primeiro Pretoriano)",
        "type": "Ocorrência",
        "image": "image/simulated_event/PicRogueEvent_4.png"
    },
    "419002": {
        "id": "419002",
        "name": "Enxame: Exploração de Ninho (Segundo Pretoriano)",
        "type": "Ocorrência",
        "image": "image/simulated_event/PicRogueEvent_4.png"
    },
    "419003": {
        "id": "419003",
        "name": "Enxame: Exploração de Ninho (Terceiro Pretoriano)",
        "type": "Ocorrência",
        "image": "image/simulated_event/PicRogueEvent_4.png"
    },
    "419201": {
        "id": "419201",
        "name": "Enxame: Mente do Domínio (Primeiro Pretoriano)",
        "type": "Ocorrência",
        "image": "image/simulated_event/PicRogueEvent_4.png"
    },
    "419202": {
        "id": "419202",
        "name": "Enxame: Mente do Domínio (Segundo Pretoriano)",
        "type": "Ocorrência",
        "image": "image/simulated_event/PicRogueEvent_4.png"
    },
    "419203": {
        "id": "419203",
        "name": "Enxame: Mente do Domínio (Terceiro Pretoriano)",
        "type": "Ocorrência",
        "image": "image/simulated_event/PicRogueEvent_4.png"
    },
    "419301": {
        "id": "419301",
        "name": "Vislumbres da Dançarina Universal",
        "type": "Ocorrência",
        "image": "image/simulated_event/PicRogueEvent_profiteer.png"
    },
    "419401": {
        "id": "419401",
        "name": "Mundo Pixelado: Estágio Oculto",
        "type": "Ocorrência",
        "image": "image/simulated_event/PicRogueEvent_Pixel.png"
    },
    "419501": {
        "id": "419501",
        "name": "Espelho da Transcendência",
        "type": "Ocorrência",
        "image": "image/simulated_event/PicRogueEvent_Normal.png"
    },
    "420101": {
        "id": "420101",
        "name": "Cidade Mecânica \"Salão de Cabeleireiro Cogito\" - Screwllita",
        "type": "Ocorrência",
        "image": "image/simulated_event/PicRogueEvent_10.png"
    },
    "420201": {
        "id": "420201",
        "name": "Cidade Mecânica \"Salão de Cabeleireiro Cogito\" - Guilda de Intelectuais",
        "type": "Ocorrência",
        "image": "image/simulated_event/PicRogueEvent_8.png"
    },
    "420301": {
        "id": "420301",
        "name": "Cidade Mecânica \"Salão de Cabeleireiro Cogito\" - Sociedade de Gênios",
        "type": "Ocorrência",
        "image": "image/simulated_event/PicRogueEvent_9.png"
    },
    "420401": {
        "id": "420401",
        "name": "Hacker de Curio",
        "type": "Ocorrência",
        "image": "image/simulated_event/PicRogueEvent_Normal.png"
    },
    "420501": {
        "id": "420501",
        "name": "Máquina de Fabricação de Cera Seladora",
        "type": "Ocorrência",
        "image": "image/simulated_event/PicRogueEvent_Normal.png"
    },
    "420601": {
        "id": "420601",
        "name": "Dispositivo de Investimento da Paz Interastral",
        "type": "Ocorrência",
        "image": "image/simulated_event/PicRogueEvent_Bond.png"
    },
    "420701": {
        "id": "420701",
        "name": "Shopping da Filial Mecânica da Paz Interastral (I)",
        "type": "Ocorrência",
        "image": "image/simulated_event/PicRogueEvent_Bond.png"
    },
    "420801": {
        "id": "420801",
        "name": "Shopping da Filial Mecânica da Paz Interastral (II)",
        "type": "Ocorrência",
        "image": "image/simulated_event/PicRogueEvent_Bond.png"
    },
    "420901": {
        "id": "420901",
        "name": "Código de Trapaça (I)",
        "type": "Ocorrência",
        "image": "image/simulated_event/PicRogueEvent_Normal.png"
    },
    "420902": {
        "id": "420902",
        "name": "Código de Trapaça (II)",
        "type": "Ocorrência",
        "image": "image/simulated_event/PicRogueEvent_Normal.png"
    },
    "421001": {
        "id": "421001",
        "name": "Alimentação Perigosa",
        "type": "Ocorrência",
        "image": "image/simulated_event/PicRogueEvent_13.png"
    },
    "421101": {
        "id": "421101",
        "name": "O Heliobus em Regresso",
        "type": "Ocorrência",
        "image": "image/simulated_event/PicRogueEvent_14.png"
    },
    "421201": {
        "id": "421201",
        "name": "Coliseu Culinário",
        "type": "Ocorrência",
        "image": "image/simulated_event/PicRogueEvent_15.png"
    },
    "421301": {
        "id": "421301",
        "name": "Guerra Ternária",
        "type": "Ocorrência",
        "image": "image/simulated_event/PicRogueEvent_16.png"
    },
    "421401": {
        "id": "421401",
        "name": "Competição Harmoniosa",
        "type": "Ocorrência",
        "image": "image/simulated_event/PicRogueEvent_18.png"
    },
    "421501": {
        "id": "421501",
        "name": "Legado Imperial",
        "type": "Ocorrência",
        "image": "image/simulated_event/PicRogueEvent_12.png"
    },
    "421601": {
        "id": "421601",
        "name": "Adivinhação",
        "type": "Ocorrência",
        "image": "image/simulated_event/PicRogueEvent_11.png"
    },
    "421701": {
        "id": "421701",
        "name": "Ruan Mei (III)",
        "type": "Ocorrência",
        "image": "image/simulated_event/PicRogueEvent_17.png"
    },
    "421801": {
        "id": "421801",
        "name": "Incompatibilidade Semântica",
        "type": "Ocorrência",
        "image": "image/simulated_event/PicRogueEvent_Battle.png"
    },
    "421901": {
        "id": "421901",
        "name": "Pão e Abacaxi",
        "type": "Ocorrência",
        "image": "image/simulated_event/PicRogueEvent_19.png"
    },
    "422001": {
        "id": "422001",
        "name": "Macacos Como Você",
        "type": "Ocorrência",
        "image": "image/simulated_event/PicRogueEvent_21.png"
    },
    "422101": {
        "id": "422101",
        "name": "Sinfonia do Lixo",
        "type": "Ocorrência",
        "image": "image/simulated_event/PicRogueEvent_20.png"
    },
    "422201": {
        "id": "422201",
        "name": "Cerimônia de Pesca",
        "type": "Ocorrência",
        "image": "image/simulated_event/PicRogueEvent_22.png"
    },
    "422301": {
        "id": "422301",
        "name": "Lava",
        "type": "Ocorrência",
        "image": "image/simulated_event/PicRogueEvent_18.png"
    },
    "422401": {
        "id": "422401",
        "name": "Desconto Especial",
        "type": "Ocorrência",
        "image": "image/simulated_event/PicRogueEvent_18.png"
    },
    "422501": {
        "id": "422501",
        "name": "Vida de Metal",
        "type": "Ocorrência",
        "image": "image/simulated_event/PicRogueEvent_Normal.png"
    },
    "422601": {
        "id": "422601",
        "name": "Uma Pitada de Cor",
        "type": "Ocorrência",
        "image": "image/simulated_event/PicRogueEvent_profiteer.png"
    },
    "422701": {
        "id": "422701",
        "name": "Unidade de Criação",
        "type": "Ocorrência",
        "image": "image/simulated_event/PicRogueEvent_Bond.png"
    },
    "422801": {
        "id": "422801",
        "name": "Banco de Tempo (I)",
        "type": "Ocorrência",
        "image": "image/simulated_event/PicRogueEvent_Trade.png"
    },
    "422811": {
        "id": "422811",
        "name": "Banco de Tempo (II)",
        "type": "Ocorrência",
        "image": "image/simulated_event/PicRogueEvent_Trade.png"
    },
    "423001": {
        "id": "423001",
        "name": "Tentação Vermelha",
        "type": "Ocorrência",
        "image": "image/simulated_event/PicRogueEvent_18.png"
    },
    "423101": {
        "id": "423101",
        "name": "Dificuldades de Seleção (I)",
        "type": "Ocorrência",
        "image": "image/simulated_event/PicRogueEvent_Twin.png"
    },
    "423102": {
        "id": "423102",
        "name": "Dificuldades de Seleção (II)",
        "type": "Ocorrência",
        "image": "image/simulated_event/PicRogueEvent_Twin.png"
    },
    "423501": {
        "id": "423501",
        "name": "Mercado de Pulgas",
        "type": "Ocorrência",
        "image": "image/simulated_event/PicRogueEvent_22.png"
    },
    "423601": {
        "id": "423601",
        "name": "Produto de Colaboração",
        "type": "Ocorrência",
        "image": "image/simulated_event/PicRogueEvent_Toy.png"
    },
    "424201": {
        "id": "424201",
        "name": "Estratégia do Oceano Azul",
        "type": "Ocorrência",
        "image": "image/simulated_event/PicRogueEvent_18.png"
    },
    "424301": {
        "id": "424301",
        "name": "Majority Report - A Velha Lei",
        "type": "Ocorrência",
        "image": "image/simulated_event/PicRogueEvent_Twin.png"
    },
    "424401": {
        "id": "424401",
        "name": "Bateu a Inspiração",
        "type": "Ocorrência",
        "image": "image/simulated_event/PicRogueEvent_29.png"
    },
    "424501": {
        "id": "424501",
        "name": "Templo da Reticência",
        "type": "Ocorrência",
        "image": "image/simulated_event/PicRogueEvent_27.png"
    },
    "424601": {
        "id": "424601",
        "name": "Futuro Falso",
        "type": "Ocorrência",
        "image": "image/simulated_event/PicRogueEvent_11.png"
    },
    "424701": {
        "id": "424701",
        "name": "Hackers e Marinheiros",
        "type": "Ocorrência",
        "image": "image/simulated_event/PicRogueEvent_28.png"
    },
    "424801": {
        "id": "424801",
        "name": "A Primeira Batalha da Rua Comercial",
        "type": "Ocorrência",
        "image": "image/simulated_event/PicRogueEvent_29.png"
    },
    "424901": {
        "id": "424901",
        "name": "A Vida É Como um Legume (I)",
        "type": "Ocorrência",
        "image": "image/simulated_event/PicRogueEvent_30.png"
    },
    "424902": {
        "id": "424902",
        "name": "A Vida É Como um Legume (II)",
        "type": "Ocorrência",
        "image": "image/simulated_event/PicRogueEvent_30.png"
    },
    "424903": {
        "id": "424903",
        "name": "A Vida É Como um Legume (III)",
        "type": "Ocorrência",
        "image": "image/simulated_event/PicRogueEvent_30.png"
    },
    "510004": {
        "id": "510004",
        "name": "Stephen",
        "type": "Ocorrência",
        "image": "image/simulated_event/HoshinoKami_Herta4.png"
    },
    "510005": {
        "id": "510005",
        "name": "Ruan Mei",
        "type": "Ocorrência",
        "image": "image/simulated_event/HoshinoKami_Herta2.png"
    },
    "519401": {
        "id": "519401",
        "name": "Mundo Pixelado: Estágio Oculto",
        "type": "Ocorrência",
        "image": "image/simulated_event/PicRogueEvent_Pixel.png"
    },
    "523801": {
        "id": "523801",
        "name": "Velozes & Motorizados",
        "type": "Ocorrência",
        "image": "image/simulated_event/PicRogueEvent_25.png"
    },
    "523901": {
        "id": "523901",
        "name": "Incubadora",
        "type": "Ocorrência",
        "image": "image/simulated_event/PicRogueEvent_23.png"
    },
    "524001": {
        "id": "524001",
        "name": "Faz Tudo (I)",
        "type": "Ocorrência",
        "image": "image/simulated_event/PicRogueEvent_24.png"
    },
    "524002": {
        "id": "524002",
        "name": "Faz Tudo (II)",
        "type": "Ocorrência",
        "image": "image/simulated_event/PicRogueEvent_24.png"
    },
    "524101": {
        "id": "524101",
        "name": "Navio dos Tolos",
        "type": "Ocorrência",
        "image": "image/simulated_event/PicRogueEvent_26.png"
    },
    "625001": {
        "id": "625001",
        "name": "Murmurador",
        "type": "Ocorrência",
        "image": "image/simulated_event/PicRogueEvent_32.png"
    },
    "625101": {
        "id": "625101",
        "name": "Familiar Impostor",
        "type": "Ocorrência",
        "image": "image/simulated_event/PicRogueEvent_34.png"
    },
    "625201": {
        "id": "625201",
        "name": "Dispositivo de Observação de Estrelas",
        "type": "Ocorrência",
        "image": "image/simulated_event/PicRogueEvent_31.png"
    },
    "625301": {
        "id": "625301",
        "name": "Dado de Dolos",
        "type": "Ocorrência",
        "image": "image/simulated_event/PicRogueEvent_34.png"
    },
    "625401": {
        "id": "625401",
        "name": "Fugitivo do Espelho",
        "type": "Ocorrência",
        "image": "image/simulated_event/PicRogueEvent_32.png"
    },
    "625501": {
        "id": "625501",
        "name": "Proporção Ideal de Sucesso",
        "type": "Ocorrência",
        "image": "image/simulated_event/PicRogueEvent_Normal.png"
    },
    "625601": {
        "id": "625601",
        "name": "Acordo Corrompido",
        "type": "Ocorrência",
        "image": "image/simulated_event/PicRogueEvent_33.png"
    },
    "625701": {
        "id": "625701",
        "name": "Voz do Mar",
        "type": "Ocorrência",
        "image": "image/simulated_event/PicRogueEvent_33.png"
    },
    "625801": {
        "id": "625801",
        "name": "Oração Apressada",
        "type": "Ocorrência",
        "image": "image/simulated_event/PicRogueEvent_31.png"
    },
    "625901": {
        "id": "625901",
        "name": "O Nascimento de um Herói (I)",
        "type": "Ocorrência",
        "image": "image/simulated_event/PicRogueEvent_32.png"
    },
    "625902": {
        "id": "625902",
        "name": "O Nascimento de um Herói (II)",
        "type": "Ocorrência",
        "image": "image/simulated_event/PicRogueEvent_32.png"
    },
    "625903": {
        "id": "625903",
        "name": "O Nascimento de um Herói (III)",
        "type": "Ocorrência",
        "image": "image/simulated_event/PicRogueEvent_32.png"
    },
    "626001": {
        "id": "626001",
        "name": "Divergência da Vida (I)",
        "type": "Ocorrência",
        "image": "image/simulated_event/PicRogueEvent_34.png"
    },
    "626002": {
        "id": "626002",
        "name": "Divergência da Vida (II)",
        "type": "Ocorrência",
        "image": "image/simulated_event/PicRogueEvent_34.png"
    },
    "626101": {
        "id": "626101",
        "name": "Teatro de Tabuleiro",
        "type": "Ocorrência",
        "image": "image/simulated_event/PicRogueEvent_31.png"
    }
}