{
    "20000": {
        "id": "20000",
        "name": "Flechas",
        "rarity": 3,
        "path": "Rogue",
        "desc": "Un extraño poder condensado a partir del tiempo. Verdaderamente, son todos los momentos insignificantes los que tejen un destino maravilloso.\n\"Los ojos del cazador ven con más claridad cuando coloca la flecha y tensa la cuerda del arco\".",
        "icon": "icon/light_cone/20000.png",
        "preview": "image/light_cone_preview/20000.png",
        "portrait": "image/light_cone_portrait/20000.png",
        "guide_overview": [
            "guide/Nwflower/light_cone/20000.png"
        ]
    },
    "20001": {
        "id": "20001",
        "name": "Cornucopia",
        "rarity": 3,
        "path": "Priest",
        "desc": "Un extraño poder condensado a partir del tiempo. Verdaderamente, son todos los momentos insignificantes los que tejen un destino maravilloso.\n\"La vida es la existencia de un orden más allá de cierto umbral. Su nacimiento es la respuesta final a un universo en un silencio de muerte. Así se declara el final de una era caótica\".",
        "icon": "icon/light_cone/20001.png",
        "preview": "image/light_cone_preview/20001.png",
        "portrait": "image/light_cone_portrait/20001.png",
        "guide_overview": [
            "guide/Nwflower/light_cone/20001.png"
        ]
    },
    "20002": {
        "id": "20002",
        "name": "Colapso celeste",
        "rarity": 3,
        "path": "Warrior",
        "desc": "Un extraño poder condensado a partir del tiempo. Verdaderamente, son todos los momentos insignificantes los que tejen un destino maravilloso.\n\"Igual que su nacimiento, es natural que las cosas vayan desvaneciéndose. El tiempo lo erosiona todo y transforma en polvo todo lo tangible\".",
        "icon": "icon/light_cone/20002.png",
        "preview": "image/light_cone_preview/20002.png",
        "portrait": "image/light_cone_portrait/20002.png",
        "guide_overview": [
            "guide/Nwflower/light_cone/20002.png"
        ]
    },
    "20003": {
        "id": "20003",
        "name": "Ámbar",
        "rarity": 3,
        "path": "Knight",
        "desc": "Un extraño poder condensado a partir del tiempo. Verdaderamente, son todos los momentos insignificantes los que tejen un destino maravilloso.\n\"Lo único que puede perdurar es lo que el tiempo no afecta\".",
        "icon": "icon/light_cone/20003.png",
        "preview": "image/light_cone_preview/20003.png",
        "portrait": "image/light_cone_portrait/20003.png",
        "guide_overview": [
            "guide/Nwflower/light_cone/20003.png"
        ]
    },
    "20004": {
        "id": "20004",
        "name": "Vacío",
        "rarity": 3,
        "path": "Warlock",
        "desc": "Un extraño poder condensado a partir del tiempo. Verdaderamente, son todos los momentos insignificantes los que tejen un destino maravilloso.\n\"Contempló el vacío, que era como un sol oscuro que se eleva al final de todas las cosas. Como una boca que tiene la respuesta a todas las preguntas, dijo: ███ █ ███ ██. Esta respuesta no se podía expresar en ningún idioma humano, pero todo el mundo la entendió\".",
        "icon": "icon/light_cone/20004.png",
        "preview": "image/light_cone_preview/20004.png",
        "portrait": "image/light_cone_portrait/20004.png",
        "guide_overview": [
            "guide/Nwflower/light_cone/20004.png"
        ]
    },
    "20005": {
        "id": "20005",
        "name": "Coro",
        "rarity": 3,
        "path": "Shaman",
        "desc": "Un extraño poder condensado a partir del tiempo. Verdaderamente, son todos los momentos insignificantes los que tejen un destino maravilloso.\n\"Los dedos forman un puño, la unión hace la fuerza. Ofrezco mi ser y obtengo algo superior: nosotros\".",
        "icon": "icon/light_cone/20005.png",
        "preview": "image/light_cone_preview/20005.png",
        "portrait": "image/light_cone_portrait/20005.png",
        "guide_overview": [
            "guide/Nwflower/light_cone/20005.png"
        ]
    },
    "20006": {
        "id": "20006",
        "name": "Archivos",
        "rarity": 3,
        "path": "Mage",
        "desc": "Un extraño poder condensado a partir del tiempo. Verdaderamente, son todos los momentos insignificantes los que tejen un destino maravilloso.\n\"La raza humana se acabará extinguiendo, pero la biblioteca perdurará: solitaria, inmóvil, escondida, silenciosa, inútil y libre de corrupción\".",
        "icon": "icon/light_cone/20006.png",
        "preview": "image/light_cone_preview/20006.png",
        "portrait": "image/light_cone_portrait/20006.png",
        "guide_overview": [
            "guide/Nwflower/light_cone/20006.png"
        ]
    },
    "20007": {
        "id": "20007",
        "name": "Flecha voladora",
        "rarity": 3,
        "path": "Rogue",
        "desc": "Un extraño poder condensado a partir del tiempo. Verdaderamente, son todos los momentos insignificantes los que tejen un destino maravilloso.\n\"La guerra ya ha comenzado. Hay que encontrar un objetivo para las flechas\".",
        "icon": "icon/light_cone/20007.png",
        "preview": "image/light_cone_preview/20007.png",
        "portrait": "image/light_cone_portrait/20007.png",
        "guide_overview": [
            "guide/Nwflower/light_cone/20007.png"
        ]
    },
    "20008": {
        "id": "20008",
        "name": "Fruto excelente",
        "rarity": 3,
        "path": "Priest",
        "desc": "Un extraño poder condensado a partir del tiempo. Verdaderamente, son todos los momentos insignificantes los que tejen un destino maravilloso.\n\"Cuando tienes sed, cualquier cosa tiene un dulce sabor\".",
        "icon": "icon/light_cone/20008.png",
        "preview": "image/light_cone_preview/20008.png",
        "portrait": "image/light_cone_portrait/20008.png",
        "guide_overview": [
            "guide/Nwflower/light_cone/20008.png"
        ]
    },
    "20009": {
        "id": "20009",
        "name": "Hogar destrozado",
        "rarity": 3,
        "path": "Warrior",
        "desc": "Un extraño poder condensado a partir del tiempo. Verdaderamente, son todos los momentos insignificantes los que tejen un destino maravilloso.\n\"Aquel que tiene la capacidad de destruir algo es quien realmente controla ese algo\".",
        "icon": "icon/light_cone/20009.png",
        "preview": "image/light_cone_preview/20009.png",
        "portrait": "image/light_cone_portrait/20009.png",
        "guide_overview": [
            "guide/Nwflower/light_cone/20009.png"
        ]
    },
    "20010": {
        "id": "20010",
        "name": "Blindaje",
        "rarity": 3,
        "path": "Knight",
        "desc": "Un extraño poder condensado a partir del tiempo. Verdaderamente, son todos los momentos insignificantes los que tejen un destino maravilloso.\n\"La resistencia de la población detrás de las murallas demuestra que defenderse también es una forma de ganar\".",
        "icon": "icon/light_cone/20010.png",
        "preview": "image/light_cone_preview/20010.png",
        "portrait": "image/light_cone_portrait/20010.png",
        "guide_overview": [
            "guide/Nwflower/light_cone/20010.png"
        ]
    },
    "20011": {
        "id": "20011",
        "name": "Bucle",
        "rarity": 3,
        "path": "Warlock",
        "desc": "Un extraño poder condensado a partir del tiempo. Verdaderamente, son todos los momentos insignificantes los que tejen un destino maravilloso.\n\"El fugitivo intenta escapar de los fantasmas del pasado, un dolor que cree que nadie más puede comprender. Hasta que levanta la cabeza y ve a su yo del futuro con sus terroríficos ojos abiertos\".",
        "icon": "icon/light_cone/20011.png",
        "preview": "image/light_cone_preview/20011.png",
        "portrait": "image/light_cone_portrait/20011.png",
        "guide_overview": [
            "guide/Nwflower/light_cone/20011.png"
        ]
    },
    "20012": {
        "id": "20012",
        "name": "Rueda mecánica",
        "rarity": 3,
        "path": "Shaman",
        "desc": "Un extraño poder condensado a partir del tiempo. Verdaderamente, son todos los momentos insignificantes los que tejen un destino maravilloso.\n\"No existe un sonido más armonioso que este. Cada uno ocupa su lugar y la enorme máquina comienza a moverse\".",
        "icon": "icon/light_cone/20012.png",
        "preview": "image/light_cone_preview/20012.png",
        "portrait": "image/light_cone_portrait/20012.png",
        "guide_overview": [
            "guide/Nwflower/light_cone/20012.png"
        ]
    },
    "20013": {
        "id": "20013",
        "name": "Llave maestra",
        "rarity": 3,
        "path": "Mage",
        "desc": "Un extraño poder condensado a partir del tiempo. Verdaderamente, son todos los momentos insignificantes los que tejen un destino maravilloso.\n\"El conocimiento siempre está tras esa puerta y la llave no la regala nadie. Quien más ansíe tenerla, puede hacerlo\".",
        "icon": "icon/light_cone/20013.png",
        "preview": "image/light_cone_preview/20013.png",
        "portrait": "image/light_cone_portrait/20013.png",
        "guide_overview": [
            "guide/Nwflower/light_cone/20013.png"
        ]
    },
    "20014": {
        "id": "20014",
        "name": "Antagonista",
        "rarity": 3,
        "path": "Rogue",
        "desc": "Un extraño poder condensado a partir del tiempo. Verdaderamente, son todos los momentos insignificantes los que tejen un destino maravilloso.\n\"Quienes luchan por la libertad nunca mueren, porque sus historias se contarán durante toda la eternidad\".",
        "icon": "icon/light_cone/20014.png",
        "preview": "image/light_cone_preview/20014.png",
        "portrait": "image/light_cone_portrait/20014.png",
        "guide_overview": [
            "guide/Nwflower/light_cone/20014.png"
        ]
    },
    "20015": {
        "id": "20015",
        "name": "Multiplicación",
        "rarity": 3,
        "path": "Priest",
        "desc": "Un extraño poder condensado a partir del tiempo. Verdaderamente, son todos los momentos insignificantes los que tejen un destino maravilloso.\n\"Cuando la vida pierde su sentido, hay que seguir dando vida\".",
        "icon": "icon/light_cone/20015.png",
        "preview": "image/light_cone_preview/20015.png",
        "portrait": "image/light_cone_portrait/20015.png",
        "guide_overview": [
            "guide/Nwflower/light_cone/20015.png"
        ]
    },
    "20016": {
        "id": "20016",
        "name": "Final mutuo",
        "rarity": 3,
        "path": "Warrior",
        "desc": "Un extraño poder condensado a partir del tiempo. Verdaderamente, son todos los momentos insignificantes los que tejen un destino maravilloso.\n\"¿Cómo lograr que el pasado de un planeta sea perfecto? Rompiéndolo en pedazos ahora mismo\".",
        "icon": "icon/light_cone/20016.png",
        "preview": "image/light_cone_preview/20016.png",
        "portrait": "image/light_cone_portrait/20016.png",
        "guide_overview": [
            "guide/Nwflower/light_cone/20016.png"
        ]
    },
    "20017": {
        "id": "20017",
        "name": "Colonización",
        "rarity": 3,
        "path": "Knight",
        "desc": "Un extraño poder condensado a partir del tiempo. Verdaderamente, son todos los momentos insignificantes los que tejen un destino maravilloso.\n\"El tiempo de la soledad ha pasado, a partir de ahora la Corporación los acompañará a todos\".",
        "icon": "icon/light_cone/20017.png",
        "preview": "image/light_cone_preview/20017.png",
        "portrait": "image/light_cone_portrait/20017.png",
        "guide_overview": [
            "guide/Nwflower/light_cone/20017.png"
        ]
    },
    "20018": {
        "id": "20018",
        "name": "Sombra oculta",
        "rarity": 3,
        "path": "Warlock",
        "desc": "Un extraño poder condensado a partir del tiempo. Verdaderamente, son todos los momentos insignificantes los que tejen un destino maravilloso.\n\"Tal vez la Nihilidad venga a nosotros, pero hay muchas más probabilidades de que no lo haga\".",
        "icon": "icon/light_cone/20018.png",
        "preview": "image/light_cone_preview/20018.png",
        "portrait": "image/light_cone_portrait/20018.png",
        "guide_overview": [
            "guide/Nwflower/light_cone/20018.png"
        ]
    },
    "20019": {
        "id": "20019",
        "name": "Mediación",
        "rarity": 3,
        "path": "Shaman",
        "desc": "Un extraño poder condensado a partir del tiempo. Verdaderamente, son todos los momentos insignificantes los que tejen un destino maravilloso.\n\"¿Acaso existe un gozo mayor que el de eliminar las discordancias?\".",
        "icon": "icon/light_cone/20019.png",
        "preview": "image/light_cone_preview/20019.png",
        "portrait": "image/light_cone_portrait/20019.png",
        "guide_overview": [
            "guide/Nwflower/light_cone/20019.png"
        ]
    },
    "20020": {
        "id": "20020",
        "name": "Sagacidad",
        "rarity": 3,
        "path": "Mage",
        "desc": "Un extraño poder condensado a partir del tiempo. Verdaderamente, son todos los momentos insignificantes los que tejen un destino maravilloso.\n\"Si los sabios no son capaces de deshacerse de su identidad como humanos, los abandonará la sabiduría\".",
        "icon": "icon/light_cone/20020.png",
        "preview": "image/light_cone_preview/20020.png",
        "portrait": "image/light_cone_portrait/20020.png",
        "guide_overview": [
            "guide/Nwflower/light_cone/20020.png"
        ]
    },
    "21000": {
        "id": "21000",
        "name": "Conversación en el postoperatorio",
        "rarity": 4,
        "path": "Priest",
        "desc": "\"Despertaste... Gracias\".\n\"Natasha... me has salvado. Yo debería ser... quien te lo agradeciera\".\n\"No, yo tengo que darte las gracias... por aguantar hasta el final de la operación\".\nDoctora y paciente sonríen débilmente y no dicen nada más.",
        "icon": "icon/light_cone/21000.png",
        "preview": "image/light_cone_preview/21000.png",
        "portrait": "image/light_cone_portrait/21000.png",
        "guide_overview": [
            "guide/Nwflower/light_cone/21000.png",
            "guide/OriginMirror/light_cone/21000.png"
        ]
    },
    "21001": {
        "id": "21001",
        "name": "Buenas noches, que duermas bien",
        "rarity": 4,
        "path": "Warlock",
        "desc": "La luz tenue delinea las huellas polvorientas y una joven habla dulcemente en sueños.\nUna silueta aparece a su lado y permanece silenciosa.\n\"Vaya, vaya, sabía que te verías más linda sin esos lentes\".\nLa guitarrista contempla su rostro dormido y murmura:\n\"Buenas noches, genio que tiene que tenerlo todo bajo control\".",
        "icon": "icon/light_cone/21001.png",
        "preview": "image/light_cone_preview/21001.png",
        "portrait": "image/light_cone_portrait/21001.png",
        "guide_overview": [
            "guide/Nwflower/light_cone/21001.png",
            "guide/OriginMirror/light_cone/21001.png"
        ]
    },
    "21002": {
        "id": "21002",
        "name": "El primer día del resto de mi vida",
        "rarity": 4,
        "path": "Knight",
        "desc": "\"¡Qué contenta estoy de ver a Pom-Pom con ropa nueva hoy! ¡Me gusta!\".\n\"¡Hoy es mi cumpleaños! Sigo viéndome igual de linda, ¿verdad?\".\n\"¡Por fiiiiin tengo a alguien a mi cargo! ¿A que sí, {NICKNAME}?\".\nPresionamos el obturador repetidas veces sin pensar.\n¿Es para capturar la felicidad del momento?\n¿O para capturarnos a nosotros mismos en ese instante?",
        "icon": "icon/light_cone/21002.png",
        "preview": "image/light_cone_preview/21002.png",
        "portrait": "image/light_cone_portrait/21002.png",
        "guide_overview": [
            "guide/Nwflower/light_cone/21002.png",
            "guide/OriginMirror/light_cone/21002.png"
        ]
    },
    "21003": {
        "id": "21003",
        "name": "Solo queda silencio",
        "rarity": 4,
        "path": "Rogue",
        "desc": "\"Ya llegamos a nuestra parada, ¿no nos bajamos?\".\nSe oyó una risita proveniente de arriba. Sus ojos se movieron, pero no levantó la cabeza.\n\"A decir verdad, Marzo siempre dice que eres muy inexpresivo, pero a mí no me lo parece\".\n\"Los archivos del tren muestran que hubo una actualización, pero no se guardó\".\n\"¿Qué entrada te estaba causando problemas?\".\nÉl apretó el bolígrafo y miró la escena sangrienta que había escrito de memoria en el cuaderno.\n\"Ah, ya veo. Es la entrada sobre ti...\".",
        "icon": "icon/light_cone/21003.png",
        "preview": "image/light_cone_preview/21003.png",
        "portrait": "image/light_cone_portrait/21003.png",
        "guide_overview": [
            "guide/Nwflower/light_cone/21003.png",
            "guide/OriginMirror/light_cone/21003.png"
        ]
    },
    "21004": {
        "id": "21004",
        "name": "Imagen en el recuerdo",
        "rarity": 4,
        "path": "Shaman",
        "desc": "En una mesa de la residencia de la Guardiana, colocada en la esquina más alejada, hay una vieja fotografía.\nSu mirada se posa ocasionalmente sobre ella, pero intenta evitarla.\nLos recuerdos del pasado se sienten muy lejanos, pero los sueños del presente aún perduran.",
        "icon": "icon/light_cone/21004.png",
        "preview": "image/light_cone_preview/21004.png",
        "portrait": "image/light_cone_portrait/21004.png",
        "guide_overview": [
            "guide/Nwflower/light_cone/21004.png",
            "guide/OriginMirror/light_cone/21004.png"
        ]
    },
    "21005": {
        "id": "21005",
        "name": "Los Topos te dan la bienvenida",
        "rarity": 4,
        "path": "Warrior",
        "desc": "\"¡Los Topos! ¡Los Topos!\".\n\"¡En marcha!\".\n\"¡Los astutos Topos no temen a nada!\".\n\"¡Los Topos! ¡Los Topos!\".\n\"¡Los Topos van de aventuras!\".",
        "icon": "icon/light_cone/21005.png",
        "preview": "image/light_cone_preview/21005.png",
        "portrait": "image/light_cone_portrait/21005.png",
        "guide_overview": [
            "guide/Nwflower/light_cone/21005.png",
            "guide/OriginMirror/light_cone/21005.png"
        ]
    },
    "21006": {
        "id": "21006",
        "name": "El nacimiento del yo",
        "rarity": 4,
        "path": "Mage",
        "desc": "Al principio, su pose era exactamente la misma que en el retrato anterior.\nAl mirar esa cara idéntica a la suya, se convenció de que no era ella.\n\"Es imposible, ¿cómo puede haber dos retratos iguales?\".\nLe retocó las articulaciones, le abrió los ojos e hizo que los dedos fueran más suaves.\nAl terminar, pareció satisfecha.\n\"Es completamente diferente a ayer. Este es mi yo de hoy\".",
        "icon": "icon/light_cone/21006.png",
        "preview": "image/light_cone_preview/21006.png",
        "portrait": "image/light_cone_portrait/21006.png",
        "guide_overview": [
            "guide/Nwflower/light_cone/21006.png",
            "guide/OriginMirror/light_cone/21006.png"
        ]
    },
    "21007": {
        "id": "21007",
        "name": "Sentimiento compartido",
        "rarity": 4,
        "path": "Priest",
        "desc": "La niña estaba herida cuando la doctora la encontró, pero seguía agarrándose con fuerza a la máquina parada. Tenía los bolsillos llenos de piezas de repuesto.\nLa llevó rápidamente a la clínica y curó sus heridas.\nLa niña tenía la frente perlada de sudor y, aunque no dijo ni una palabra, sus manos no se quedaron quietas ni un instante.\nLa doctora sabía que, en ese momento, la niña solo podía pensar en esa máquina, como ella misma solo pensaba en sus pacientes que requerían tratamiento.\nPor eso no pronunció ninguna palabra de consuelo, ni tampoco le advirtió de que tuviera más cuidado la próxima vez, sino que simplemente se quedó sentada a su lado y le hizo compañía en silencio.",
        "icon": "icon/light_cone/21007.png",
        "preview": "image/light_cone_preview/21007.png",
        "portrait": "image/light_cone_portrait/21007.png",
        "guide_overview": [
            "guide/Nwflower/light_cone/21007.png",
            "guide/OriginMirror/light_cone/21007.png"
        ]
    },
    "21008": {
        "id": "21008",
        "name": "Visión de presa",
        "rarity": 4,
        "path": "Warlock",
        "desc": "En realidad, la mayoría de las presas no se dan cuenta del peligro que las acecha.\nEsta vez no es una excepción.\nEl visor gira lentamente y se fija en un hombre que arroja sin cesar un fajo de billetes tras otro.\n\"Mira qué avaricioso. Con ese dinero yo podría hacer varios negocios... No me extraña que haya gente que quiera acabar con él\".\nComo si lo hubiera oído, el hombre vuelve la cabeza.\n\"Llevo mucho tiempo esperándote. ¿Este dinero es suficiente para que escuches mi oferta antes de tomar una decisión?\".",
        "icon": "icon/light_cone/21008.png",
        "preview": "image/light_cone_preview/21008.png",
        "portrait": "image/light_cone_portrait/21008.png",
        "guide_overview": [
            "guide/Nwflower/light_cone/21008.png",
            "guide/OriginMirror/light_cone/21008.png"
        ]
    },
    "21009": {
        "id": "21009",
        "name": "La elección de Landau",
        "rarity": 4,
        "path": "Knight",
        "desc": "\"¿No me has escuchado? ¡No vuelvas a ir allí nunca más! ¡¿Se puede aprender algo bueno con un grupo de plebeyos?!\".\n\"Pero nunca he oído hablar de las historias que cuentan de Belobog...\".\nSe llevó a su hermano detrás de ella, negándole la posibilidad de replicar.\n\"¡Los dos son Landau! Un día, se enfrentarán a decisiones difíciles. Especialmente tú, Serval\".\nSabía que su hermano no había hecho nada malo, pero no se le ocurría nada que replicar.\nSe fue a la cama enfadada después de la discusión, prometiéndose a sí misma:\n\"Algún día seré adulta. Y cuando llegue ese día, yo tomaré las decisiones...\".\n\"Mis propias decisiones...\".",
        "icon": "icon/light_cone/21009.png",
        "preview": "image/light_cone_preview/21009.png",
        "portrait": "image/light_cone_portrait/21009.png",
        "guide_overview": [
            "guide/Nwflower/light_cone/21009.png",
            "guide/OriginMirror/light_cone/21009.png"
        ]
    },
    "21010": {
        "id": "21010",
        "name": "Juego de espadas",
        "rarity": 4,
        "path": "Rogue",
        "desc": "La chica blande escéptica el estoque que tiene en la mano.\nSu espada solo se puede levantar con las dos manos. ¿Esta cosa tan ligera también es una espada? ¿Y sirve para matar enemigos?\nAl dueño de la espada todo esto le resulta indiferente, al fin y al cabo...\nMatar enemigos no depende de la espada, sino del corazón.\n¿Qué más da utilizar una espada pesada o una ligera?",
        "icon": "icon/light_cone/21010.png",
        "preview": "image/light_cone_preview/21010.png",
        "portrait": "image/light_cone_portrait/21010.png",
        "guide_overview": [
            "guide/Nwflower/light_cone/21010.png",
            "guide/OriginMirror/light_cone/21010.png"
        ]
    },
    "21011": {
        "id": "21011",
        "name": "Encuentro planetario",
        "rarity": 4,
        "path": "Shaman",
        "desc": "Cuando se puso en marcha, no sabía nada sobre este largo viaje.\nLo único que sabía es que al fin podría despedirse de las mil lenguas que había en casa y escapar de los continuos ataques.\nAl mirar por la ventana, finalmente comprendió el significado de ese poema.\n\"Después de cierto punto ya no andamos, sino que volamos\".\nLa luz brillante que relucía en sus ojos era el reflejo de los planetas.",
        "icon": "icon/light_cone/21011.png",
        "preview": "image/light_cone_preview/21011.png",
        "portrait": "image/light_cone_portrait/21011.png",
        "guide_overview": [
            "guide/Nwflower/light_cone/21011.png",
            "guide/OriginMirror/light_cone/21011.png"
        ]
    },
    "21012": {
        "id": "21012",
        "name": "Juramento secreto",
        "rarity": 4,
        "path": "Warrior",
        "desc": "Antes de salir, el joven siempre revisaba cuidadosamente las coderas y los guantes.\nEsos eran sus guantes favoritos, lo suficientemente ajustados como para esconder muchos secretos.\nDe esta forma, nadie podía ver las vendas que le cubrían las manos, ni las heridas que había debajo.\nTodo el mundo lo trataba como a una persona normal y lo saludaba de forma normal.\nCon eso bastaba.",
        "icon": "icon/light_cone/21012.png",
        "preview": "image/light_cone_preview/21012.png",
        "portrait": "image/light_cone_portrait/21012.png",
        "guide_overview": [
            "guide/Nwflower/light_cone/21012.png",
            "guide/OriginMirror/light_cone/21012.png"
        ]
    },
    "21013": {
        "id": "21013",
        "name": "Que el mundo clame",
        "rarity": 4,
        "path": "Mage",
        "desc": "Agitó la mano desde el escenario, con el deseo de que todo el mundo la siguiera y se oyeran sus voces.\nPodían cantar, gritar, llorar, todo valía.\nQue tu voz resuene hasta que alguien la oiga, así otros se unirán.\n\"Que no se enfríen los corazones y se vuelvan tan gélidos como esta ciudad\".\nQue el mundo clame.",
        "icon": "icon/light_cone/21013.png",
        "preview": "image/light_cone_preview/21013.png",
        "portrait": "image/light_cone_portrait/21013.png",
        "guide_overview": [
            "guide/Nwflower/light_cone/21013.png",
            "guide/OriginMirror/light_cone/21013.png"
        ]
    },
    "21014": {
        "id": "21014",
        "name": "El momento oportuno",
        "rarity": 4,
        "path": "Priest",
        "desc": "Camina por una calle bulliciosa y el sol sigue sus pasos.\nSe detiene un momento y toma un parasol para protegerse de sus rayos...\ny de esa mirada fisgona.",
        "icon": "icon/light_cone/21014.png",
        "preview": "image/light_cone_preview/21014.png",
        "portrait": "image/light_cone_portrait/21014.png",
        "guide_overview": [
            "guide/Nwflower/light_cone/21014.png",
            "guide/OriginMirror/light_cone/21014.png"
        ]
    },
    "21015": {
        "id": "21015",
        "name": "Determinación reluciente",
        "rarity": 4,
        "path": "Warlock",
        "desc": "Las luces del ring de boxeo relucen con fuerza, pero no brillan tanto como las gotas de sudor que bajan por su espalda.\nHace tiempo que decidió usar sus puños para proteger a aquellos a los que quiere.\nAl fin y al cabo, ellos fueron quienes prendieron su determinación.\nEllos son los que siempre han estado ahí, ya sea dentro o fuera del ring.",
        "icon": "icon/light_cone/21015.png",
        "preview": "image/light_cone_preview/21015.png",
        "portrait": "image/light_cone_portrait/21015.png",
        "guide_overview": [
            "guide/Nwflower/light_cone/21015.png",
            "guide/OriginMirror/light_cone/21015.png"
        ]
    },
    "21016": {
        "id": "21016",
        "name": "Tendencias del mercado universal",
        "rarity": 4,
        "path": "Knight",
        "desc": "Se está reevaluando el valor del planeta...\n\"¿Este proyecto demostrará que cobrar las deudas es beneficioso para ambas partes?\".\n\"Pero solo necesitamos transmitir un mensaje: que existimos\".\n\"Si quiere tener su propio valor, debe aportar valor a la Corporación\".",
        "icon": "icon/light_cone/21016.png",
        "preview": "image/light_cone_preview/21016.png",
        "portrait": "image/light_cone_portrait/21016.png",
        "guide_overview": [
            "guide/Nwflower/light_cone/21016.png",
            "guide/OriginMirror/light_cone/21016.png"
        ]
    },
    "21017": {
        "id": "21017",
        "name": "¡Suscríbanse a mi canal!",
        "rarity": 4,
        "path": "Rogue",
        "desc": "\"¡Hey, hey! ¿Me reciben? ¿Llega bien la señal?\".\nLa chica pelirroja levanta un martillo frente a la cámara mientras grita con entusiasmo.\n\"¿Han visto alguna vez a una hermosa chica romperse una roca enorme encima del pecho?\".\n\"¡No me uní a los Nimbocaballeros para hacer cosas así!\", grita la chica morena mientras la pelirroja sonríe de forma taimada.\n\"¡Vamos! ¡Esto también se considera ayudar a los demás!\".",
        "icon": "icon/light_cone/21017.png",
        "preview": "image/light_cone_preview/21017.png",
        "portrait": "image/light_cone_portrait/21017.png",
        "guide_overview": [
            "guide/Nwflower/light_cone/21017.png",
            "guide/OriginMirror/light_cone/21017.png"
        ]
    },
    "21018": {
        "id": "21018",
        "name": "¡A bailar!",
        "rarity": 4,
        "path": "Shaman",
        "desc": "\"Hook, ¿por qué no puedes girar cuando bailas, igual que yo?\".\nLa niña apretó los puños e hizo un puchero. Debajo de su característico sombrero de fieltro, su cara regordeta estaba más sonrojada que nunca.\n\"Señor Svarog, ayude a Hook, por favor\".\nSin decir palabra, el enorme robot extendió su brazo robótico.\n\"Me... ¡me estoy mareando! ¡Suéltame!\".",
        "icon": "icon/light_cone/21018.png",
        "preview": "image/light_cone_preview/21018.png",
        "portrait": "image/light_cone_portrait/21018.png",
        "guide_overview": [
            "guide/Nwflower/light_cone/21018.png",
            "guide/OriginMirror/light_cone/21018.png"
        ]
    },
    "21019": {
        "id": "21019",
        "name": "Bajo el cielo azul",
        "rarity": 4,
        "path": "Warrior",
        "desc": "Los trigales danzaban bajo el cielo azul.\nLa niña estaba trenzando con mucho cuidado una corona de flores para su hermana pequeña preferida.\nEn ese momento, todavía eran igual de altas.\nEn ese momento, las dos tenían la misma sonrisa.",
        "icon": "icon/light_cone/21019.png",
        "preview": "image/light_cone_preview/21019.png",
        "portrait": "image/light_cone_portrait/21019.png",
        "guide_overview": [
            "guide/Nwflower/light_cone/21019.png",
            "guide/OriginMirror/light_cone/21019.png"
        ]
    },
    "21020": {
        "id": "21020",
        "name": "El reposo de los genios",
        "rarity": 4,
        "path": "Mage",
        "desc": "Señaló con el dedo el pastelillo verde.\n\"El experimento ha terminado, es hora de descansar. ¡Tengo que tomarme este pastelillo recién salido del horno ahora mismo!\".\nVio cómo la marioneta fruncía el ceño y se quedaba pensativa.\n\"Con tu cuerpo actual, solo puedes mirar, no comer. Cuando llegue el momento, te daré una caja entera\".\nObservó cómo el aristocrático robot levantaba su vaso con aire de tristeza.\n\"No te preocupes, solo es aceite de motor. Puedes tomarlo sin problema\".",
        "icon": "icon/light_cone/21020.png",
        "preview": "image/light_cone_preview/21020.png",
        "portrait": "image/light_cone_portrait/21020.png",
        "guide_overview": [
            "guide/Nwflower/light_cone/21020.png",
            "guide/OriginMirror/light_cone/21020.png"
        ]
    },
    "21021": {
        "id": "21021",
        "name": "Intercambio equivalente",
        "rarity": 4,
        "path": "Priest",
        "desc": "Después de disfrutar de un vigoroso masaje de la chica dragón, la joven raposiana extendió las manos y pellizcó cariñosamente las mejillas regordetas de la chica.\nLa chica frunció los labios, claramente ofendida, y la joven raposiana soltó una risa alegre.\n\"Esto es lo que yo llamo un intercambio equivalente\".",
        "icon": "icon/light_cone/21021.png",
        "preview": "image/light_cone_preview/21021.png",
        "portrait": "image/light_cone_portrait/21021.png",
        "guide_overview": [
            "guide/Nwflower/light_cone/21021.png",
            "guide/OriginMirror/light_cone/21021.png"
        ]
    },
    "21022": {
        "id": "21022",
        "name": "Calderón",
        "rarity": 4,
        "path": "Warlock",
        "desc": "El disco del fonógrafo gira sin parar e incluso los gritos roncos se humedecen con el aire caliente.\nParece que ella no estaba preparada y permanece fascinada ante esas melodías sorprendentes.\nComenzó con sinceridad y expectación.\nSiguió una catarsis apasionada\ncon un clímax tras otro...\nHasta que el disco se detuvo y ya no se oían los gritos sordos.\n\"Misión cumplida\".",
        "icon": "icon/light_cone/21022.png",
        "preview": "image/light_cone_preview/21022.png",
        "portrait": "image/light_cone_portrait/21022.png",
        "guide_overview": [
            "guide/Nwflower/light_cone/21022.png",
            "guide/OriginMirror/light_cone/21022.png"
        ]
    },
    "21023": {
        "id": "21023",
        "name": "Somos Llamarada",
        "rarity": 4,
        "path": "Knight",
        "desc": "Estaba acostumbrada a que la gente perdiera su hogar, y también a que perdieran la vida... pero llorar cuando estaba sola no servía de nada.\n\"Ponte este pañuelo rojo y compartiremos nuestro dolor\".\n\"Somos una familia. Somos Llamarada\".\nCuando esas manos grandes le acariciaron la cabeza, no pudo contener las lágrimas.",
        "icon": "icon/light_cone/21023.png",
        "preview": "image/light_cone_preview/21023.png",
        "portrait": "image/light_cone_portrait/21023.png",
        "guide_overview": [
            "guide/Nwflower/light_cone/21023.png",
            "guide/OriginMirror/light_cone/21023.png"
        ]
    },
    "21024": {
        "id": "21024",
        "name": "El río nace en primavera",
        "rarity": 4,
        "path": "Rogue",
        "desc": "El niño se tomó un breve descanso de su entrenamiento con la espada.\nEl sol le estaba friendo la nuca, que ya tenía caliente de por sí.\nSe metió lentamente en el agua. Solo le llegaba a los pies y estaba fría, pero cuando suenan las campanas y pían los pájaros, hasta quienes están lejos saben que ha llegado la primavera.",
        "icon": "icon/light_cone/21024.png",
        "preview": "image/light_cone_preview/21024.png",
        "portrait": "image/light_cone_portrait/21024.png",
        "guide_overview": [
            "guide/Nwflower/light_cone/21024.png",
            "guide/OriginMirror/light_cone/21024.png"
        ]
    },
    "21025": {
        "id": "21025",
        "name": "El pasado y el futuro",
        "rarity": 4,
        "path": "Shaman",
        "desc": "Las alas de la cometa de papel que tenía entre las manos estaban rotas, lo que le recordaba su trágica pérdida.\nSe arrodilló junto al fuego de la guerra con los ojos llenos de tristeza.\n\"Si solo tú puedes salvarnos, entonces nuestro sacrificio...\".\nLos disparos continuaban y coloreaban de rojo el firmamento, sin oscurecer su majestuosidad.\nDirigió la vista hacia arriba. En sus ojos brillaba la furia.",
        "icon": "icon/light_cone/21025.png",
        "preview": "image/light_cone_preview/21025.png",
        "portrait": "image/light_cone_portrait/21025.png",
        "guide_overview": [
            "guide/Nwflower/light_cone/21025.png",
            "guide/OriginMirror/light_cone/21025.png"
        ]
    },
    "21026": {
        "id": "21026",
        "name": "¡Guau! ¡Hora de pasear!",
        "rarity": 4,
        "path": "Warrior",
        "desc": "Es una pena que nadie lo vea...\nCómo arruga la nariz, olisquea por todas partes y se mete por una ruta donde no hay nadie.\nEs una pena que nadie lo vea...\nCómo esconde las garras, introduce la contraseña y salta hacia la libertad.\n¿Aún no lo ha visto nadie?\n¡Un perro adulto de pequeño tamaño que ha aprendido a pasearse solito por el espacio!",
        "icon": "icon/light_cone/21026.png",
        "preview": "image/light_cone_preview/21026.png",
        "portrait": "image/light_cone_portrait/21026.png",
        "guide_overview": [
            "guide/Nwflower/light_cone/21026.png",
            "guide/OriginMirror/light_cone/21026.png"
        ]
    },
    "21027": {
        "id": "21027",
        "name": "La solemnidad del desayuno",
        "rarity": 4,
        "path": "Mage",
        "desc": "Aunque la mesa está puesta...\nAntes alguien quiere beber una taza de té.\nAntes alguien quiere tomar unas fotos.\nAntes alguien quiere leer el periódico.\nAntes alguien quiere escribir en su cuaderno.\nAntes alguien quiere jugar con su teléfono.\n\"¡Coman mientras la comida aún está caliente!\".",
        "icon": "icon/light_cone/21027.png",
        "preview": "image/light_cone_preview/21027.png",
        "portrait": "image/light_cone_portrait/21027.png",
        "guide_overview": [
            "guide/Nwflower/light_cone/21027.png",
            "guide/OriginMirror/light_cone/21027.png"
        ]
    },
    "21028": {
        "id": "21028",
        "name": "Las noches cálidas no duran",
        "rarity": 4,
        "path": "Priest",
        "desc": "Encendió una luz y miró a la amiga que estaba a su lado mientras sostenía una taza de chocolate caliente.\nLa vio leer los libros y los apuntes que le había regalado.\nLa vio lucir una inusual sonrisa.\nEn noches tan frías como esta, hasta la más mínima alegría puede ahuyentar los escalofríos.",
        "icon": "icon/light_cone/21028.png",
        "preview": "image/light_cone_preview/21028.png",
        "portrait": "image/light_cone_portrait/21028.png",
        "guide_overview": [
            "guide/Nwflower/light_cone/21028.png",
            "guide/OriginMirror/light_cone/21028.png"
        ]
    },
    "21029": {
        "id": "21029",
        "name": "Volveremos a encontrarnos",
        "rarity": 4,
        "path": "Warlock",
        "desc": "Ella sospechaba que se trataba de algún tipo de programa. Si no, ¿cómo es que nunca se cansaba?\nPero un programa nunca descartaría por iniciativa propia la mejor solución y evitaría su trampa.\n\"Parece que tendremos una batalla prolongada\", dijo bostezando.\n\"Vete a dormir. Las formas de vida orgánicas necesitan descansar\".\nEl lugar se oscureció.\nSe despertó de repente, pero los restos de los datos ya se habían destruido. Todo parecía un sueño, mas el sabor de la derrota era auténtico.",
        "icon": "icon/light_cone/21029.png",
        "preview": "image/light_cone_preview/21029.png",
        "portrait": "image/light_cone_portrait/21029.png",
        "guide_overview": [
            "guide/Nwflower/light_cone/21029.png",
            "guide/OriginMirror/light_cone/21029.png"
        ]
    },
    "21030": {
        "id": "21030",
        "name": "¡Así soy yo!",
        "rarity": 4,
        "path": "Knight",
        "desc": "La joven podía lucir cualquier atuendo, pero no estaba satisfecha, a juzgar por la docena de conjuntos de ropa amontonados detrás de ella.\n\"¿Será hoy la última vez?\", pensó en silencio. Miró a la chica reflejada en el espejo. Hoy se veía más feliz.\n\"Bien, ¡así soy yo!\".",
        "icon": "icon/light_cone/21030.png",
        "preview": "image/light_cone_preview/21030.png",
        "portrait": "image/light_cone_portrait/21030.png",
        "guide_overview": [
            "guide/Nwflower/light_cone/21030.png",
            "guide/OriginMirror/light_cone/21030.png"
        ]
    },
    "21031": {
        "id": "21031",
        "name": "Regreso a la oscuridad",
        "rarity": 4,
        "path": "Rogue",
        "desc": "Aunque estaba al lado de su hermana, no oía nada.\nLa voz del fondo de su corazón era cada vez más fuerte.\n\"El cuerpo de mi hermana está frío\".\n\"El cuerpo de mi hermana no se mueve\".\nLas oleadas de furia la abrumaban tanto que no tuvo tiempo de despejar su mente y recordar un detalle muy importante...\n\"El cuerpo de mi hermana ha estado frío durante mucho tiempo\".",
        "icon": "icon/light_cone/21031.png",
        "preview": "image/light_cone_preview/21031.png",
        "portrait": "image/light_cone_portrait/21031.png",
        "guide_overview": [
            "guide/Nwflower/light_cone/21031.png",
            "guide/OriginMirror/light_cone/21031.png"
        ]
    },
    "21032": {
        "id": "21032",
        "name": "Esculpir la luna y tejer las nubes",
        "rarity": 4,
        "path": "Shaman",
        "desc": "Se había enamorado al instante de aquel recipiente dorado y estaba a punto de comprarlo.\nPero la chica raposiana lo llevó a un lado y susurró:\n\"Es mejor que regrese esta noche, benefactor. Decídase entonces\".\nRegresó al caer la noche.\nQuien abrió la puerta, sonriente, era de nuevo esa chica raposiana.\n\"Sígame, benefactor\".\nUn rayo de luna se reflejó en la base del plato grabado.\nEl artesano había labrado los pétalos con líneas de distintas profundidades, detalles que solo podían percibirse a la luz de la luna.\nPor fin recordó por qué este objeto se llamaba \"esculpir la luna y tejer las nubes\".",
        "icon": "icon/light_cone/21032.png",
        "preview": "image/light_cone_preview/21032.png",
        "portrait": "image/light_cone_portrait/21032.png",
        "guide_overview": [
            "guide/Nwflower/light_cone/21032.png",
            "guide/OriginMirror/light_cone/21032.png"
        ]
    },
    "21033": {
        "id": "21033",
        "name": "Sin escapatoria",
        "rarity": 4,
        "path": "Warrior",
        "desc": "No era la primera vez que veía a ese hombre.\nNo sabía desde cuándo se había convertido en su sombra.\nNo importaba cuántas veces atravesara al hombre con su lanza; siempre regresaba.\nNo podía perder, pero tampoco ganar.\nQuería huir, pero no tenía escapatoria.",
        "icon": "icon/light_cone/21033.png",
        "preview": "image/light_cone_preview/21033.png",
        "portrait": "image/light_cone_portrait/21033.png",
        "guide_overview": [
            "guide/Nwflower/light_cone/21033.png",
            "guide/OriginMirror/light_cone/21033.png"
        ]
    },
    "21034": {
        "id": "21034",
        "name": "Hoy es otro día tranquilo",
        "rarity": 4,
        "path": "Mage",
        "desc": "Se le acababa de ocurrir una nueva forma de jugar y tenía un libro preparado para la hora del descanso.\nSi trabajaba despacio, lo que le quedaba por hacer le tomaría exactamente hasta el final de la jornada.\nSin apresurarse, se ocultó en una esquina.\nNadie debía molestarla en su maravilloso momento de descanso.\nNi siquiera la Gran Adivina.\nPero, por si apareciera...\n\"Le daré este bollito. ¡No puede enfadarse con algo dulce en la boca!\".",
        "icon": "icon/light_cone/21034.png",
        "preview": "image/light_cone_preview/21034.png",
        "portrait": "image/light_cone_portrait/21034.png",
        "guide_overview": [
            "guide/Nwflower/light_cone/21034.png",
            "guide/OriginMirror/light_cone/21034.png"
        ]
    },
    "23000": {
        "id": "23000",
        "name": "Noche en la Vía Láctea",
        "rarity": 5,
        "path": "Mage",
        "desc": "Si te preocupa el estado del camino, mira al frente de nuevo.\nCuando las estrellas nos contemplan, el corazón ya vuela en el viento.\nCada pensamiento, cada susurro,\nse convierte en una experiencia vital que nunca se irá.",
        "icon": "icon/light_cone/23000.png",
        "preview": "image/light_cone_preview/23000.png",
        "portrait": "image/light_cone_portrait/23000.png",
        "guide_overview": [
            "guide/Nwflower/light_cone/23000.png",
            "guide/OriginMirror/light_cone/23000.png"
        ]
    },
    "23001": {
        "id": "23001",
        "name": "En la noche",
        "rarity": 5,
        "path": "Rogue",
        "desc": "La joven sonríe sutilmente.\n\"¿Por qué?\".\n\"Es obvio que estoy sola, en este momento y en este lugar...\".\n\"Pero se siente... muy animado\".",
        "icon": "icon/light_cone/23001.png",
        "preview": "image/light_cone_preview/23001.png",
        "portrait": "image/light_cone_portrait/23001.png",
        "guide_overview": [
            "guide/Nwflower/light_cone/23001.png",
            "guide/OriginMirror/light_cone/23001.png"
        ]
    },
    "23002": {
        "id": "23002",
        "name": "Algo insustituible",
        "rarity": 5,
        "path": "Warrior",
        "desc": "\"Svarog, si algún día yo no estoy, tendrás que hacerte cargo de la base de datos\".\n(¿Quién es? ¿Por qué hay un mensaje así en mis registros?).\n\"Svarog, ¿hay algo que sea insustituible para ti?\".\n(¿Insustituible?... Las piezas que se rompen se sustituyen y ya está...).\n\"Svarog, algún día lo encontrarás\".\n(Esas cosas... solo traerán problemas...).\n\"Cuando llegue ese momento, vete de aquí\".",
        "icon": "icon/light_cone/23002.png",
        "preview": "image/light_cone_preview/23002.png",
        "portrait": "image/light_cone_portrait/23002.png",
        "guide_overview": [
            "guide/Nwflower/light_cone/23002.png",
            "guide/OriginMirror/light_cone/23002.png"
        ]
    },
    "23003": {
        "id": "23003",
        "name": "La batalla no ha terminado",
        "rarity": 5,
        "path": "Shaman",
        "desc": "\"Recuerden, la guerra contra esos monstruos no se puede ganar retirándose\".\n\"Detrás de nosotros está Belobog, somos la última línea de defensa...\".\n\"¡No podemos retirarnos bajo ninguna circunstancia!\".\nLevantó la cabeza y miró la tierra helada y el invierno interminable.\nOtro día normal.\nLo único diferente era que la espalda que solía contemplar ya no estaba.",
        "icon": "icon/light_cone/23003.png",
        "preview": "image/light_cone_preview/23003.png",
        "portrait": "image/light_cone_portrait/23003.png",
        "guide_overview": [
            "guide/Nwflower/light_cone/23003.png",
            "guide/OriginMirror/light_cone/23003.png"
        ]
    },
    "23004": {
        "id": "23004",
        "name": "En nombre del mundo",
        "rarity": 5,
        "path": "Warlock",
        "desc": "\"¿Welt?\".\n\"Es un buen nombre, ¿verdad?\".\n\"Entonces...\".\n\"A partir de ahora, serás Welt\".\n\"Este núcleo de Herrscher... y la misión de proteger el mundo...\".\n\"Ahora son tuyos, Welt\".",
        "icon": "icon/light_cone/23004.png",
        "preview": "image/light_cone_preview/23004.png",
        "portrait": "image/light_cone_portrait/23004.png",
        "guide_overview": [
            "guide/Nwflower/light_cone/23004.png",
            "guide/OriginMirror/light_cone/23004.png"
        ]
    },
    "23005": {
        "id": "23005",
        "name": "El momento de la victoria",
        "rarity": 5,
        "path": "Knight",
        "desc": "\"Gepard, si quieres llorar cuando pierdas, hazlo\".\n\"Pero tienes que volver a levantarte hasta que puedas ganarme... aunque tardes cinco o diez años\".\nVarios años después, el niño ya no lloraba ni perdía ante su hermana mayor.\nHoy en día, y sin importar cuál sea la situación en el campo de batalla, el intrépido capitán de la Guardia Crinargenta se mantiene firme hasta el final...\nPara encontrar el momento exacto en el que aplastará a sus enemigos.",
        "icon": "icon/light_cone/23005.png",
        "preview": "image/light_cone_preview/23005.png",
        "portrait": "image/light_cone_portrait/23005.png",
        "guide_overview": [
            "guide/Nwflower/light_cone/23005.png",
            "guide/OriginMirror/light_cone/23005.png"
        ]
    },
    "23010": {
        "id": "23010",
        "name": "Antes del amanecer",
        "rarity": 5,
        "path": "Mage",
        "desc": "\"General, este asunto no se puede decidir a la ligera... Piense en cómo lo recordarán las generaciones venideras...\".\nEl general de los Nimbocaballeros frunció el ceño al escuchar estas palabras.\n\"La historia hará su propio juicio, pero no me interesa qué opinen los demás de mí\".\n\"Si tengo éxito, dirán que todo salió de acuerdo a mi plan maestro\".\n\"Si fracaso, afirmarán que era un hedonista sin remedio y que no sabía distinguir los asuntos importantes\".\nUn pajarillo saltó desde su hombro y él levantó la mano para que aterrizara en ella.\n\"Estoy actuando de acuerdo a mi juicio\".",
        "icon": "icon/light_cone/23010.png",
        "preview": "image/light_cone_preview/23010.png",
        "portrait": "image/light_cone_portrait/23010.png",
        "guide_overview": [
            "guide/Nwflower/light_cone/23010.png",
            "guide/OriginMirror/light_cone/23010.png"
        ]
    },
    "23012": {
        "id": "23012",
        "name": "Dormir como un tronco",
        "rarity": 5,
        "path": "Rogue",
        "desc": "El joven sigue agarrando con fuerza la espada, incluso cuando se duerme apoyado en el hombro del general.\nEste roza la mejilla del joven, quien murmura algo en sueños.\n\"General... por fin... gané...\".\nEl general se queda quieto y de repente se da cuenta de que, comparado con el joven, que cada día se esfuerza por mejorar, por él ya han pasado muchos años y se ha acostumbrado a no cambiar.\n\"Muy pronto ganarás a todo el mundo, y eso solo será el comienzo...\".",
        "icon": "icon/light_cone/23012.png",
        "preview": "image/light_cone_preview/23012.png",
        "portrait": "image/light_cone_portrait/23012.png",
        "guide_overview": [
            "guide/Nwflower/light_cone/23012.png",
            "guide/OriginMirror/light_cone/23012.png"
        ]
    },
    "23013": {
        "id": "23013",
        "name": "El tiempo no espera",
        "rarity": 5,
        "path": "Priest",
        "desc": "Había pasado muchos días al lado de la ventana.\nAfuera, las flores extendían orgullosamente sus pétalos mientras ella hacía remedios suaves con menta y nepeta.\nLa lluvia caía mientras fabricaba remedios fuertes con mosla y jengibre.\nLas hojas volaban mientras hacía remedios ácidos con raíces de peonía y ciruelas secas.\nLa nieve caía mientras producía remedios amargos con escutelaria y anemarrena.\nEl tiempo nunca se detiene, pero esta ventana y la persona sentada junto a ella siguen siendo las mismas.",
        "icon": "icon/light_cone/23013.png",
        "preview": "image/light_cone_preview/23013.png",
        "portrait": "image/light_cone_portrait/23013.png",
        "guide_overview": [
            "guide/Nwflower/light_cone/23013.png",
            "guide/OriginMirror/light_cone/23013.png"
        ]
    },
    "24000": {
        "id": "24000",
        "name": "Sobre la caída de un Eón",
        "rarity": 5,
        "path": "Warrior",
        "desc": "Todo comenzó con un rayo de luz.\nUno por uno, cayeron cuando la amenaza de la exterminación se cernía sobre ellos.\nDejaron de autorreplicarse, se abrazaron entre ellos e intentaron ofrecer el derecho a la reproducción a cambio de la posibilidad de que su existencia continuara.\nSe tomaron de las manos en una muestra de unidad sin precedentes.\nPero las Vías han llegado a un final abrupto y se dirigen a la auténtica muerte.",
        "icon": "icon/light_cone/24000.png",
        "preview": "image/light_cone_preview/24000.png",
        "portrait": "image/light_cone_portrait/24000.png",
        "guide_overview": [
            "guide/Nwflower/light_cone/24000.png",
            "guide/OriginMirror/light_cone/24000.png"
        ]
    },
    "24001": {
        "id": "24001",
        "name": "Crucero estelar",
        "rarity": 5,
        "path": "Rogue",
        "desc": "Navegando por el océano de estrellas, su velocidad es como un rayo arcoíris.\nPersigue a las abominaciones no muertas, busca el antídoto contra el tesoro ilusorio, ansía un viaje de liberación.\nSu trayecto es como un juramento que nunca se rompe, hasta el infinito.",
        "icon": "icon/light_cone/24001.png",
        "preview": "image/light_cone_preview/24001.png",
        "portrait": "image/light_cone_portrait/24001.png",
        "guide_overview": [
            "guide/Nwflower/light_cone/24001.png",
            "guide/OriginMirror/light_cone/24001.png"
        ]
    },
    "24002": {
        "id": "24002",
        "name": "La textura de los recuerdos",
        "rarity": 5,
        "path": "Knight",
        "desc": "El universo era un erial cubierto de basura.\nEntre los desechos había algún tesoro que esperaba a que lo descubrieran.\nMira por las rendijas del pasado y elige las semillas de la memoria.\nSi brota una nueva vida, su semilla tiene que morir.\nAparecieron piedras preciosas de color rosa, azul y blanco\nque relucían en su campo de cultivo, pero el universo se mantuvo en silencio.",
        "icon": "icon/light_cone/24002.png",
        "preview": "image/light_cone_preview/24002.png",
        "portrait": "image/light_cone_portrait/24002.png",
        "guide_overview": [
            "guide/Nwflower/light_cone/24002.png",
            "guide/OriginMirror/light_cone/24002.png"
        ]
    },
    "29000": {
        "id": "29000",
        "name": "",
        "rarity": 3,
        "path": "",
        "desc": "",
        "icon": "",
        "preview": "",
        "portrait": "",
        "guide_overview": []
    }
}